<?xml version="1.0" ?><timetable station="Rosenheim" eva="8000320">

<s id="8886873108514141831-2509111341-7" eva="8000320">
    <ar ct="2509111427" l="RB54">
        <m id="r24796545" t="f" c="1000" ts="2509110453" ts-tts="25-09-11 04:54:13.949"/>
        <m id="r24796641" t="d" c="31" ts="2509110454" ts-tts="25-09-11 04:54:13.949"/>
        <m id="r24796644" t="d" c="31" ts="2509110454" ts-tts="25-09-11 04:54:13.949"/>
        <m id="r24796646" t="d" c="31" ts="2509110454" ts-tts="25-09-11 04:54:13.949"/>
    </ar>
    <dp ct="2509111431" l="RB54">
        <m id="r24796545" t="f" c="1000" ts="2509110453" ts-tts="25-09-11 04:54:13.949"/>
        <m id="r24796641" t="d" c="31" ts="2509110454" ts-tts="25-09-11 04:54:13.949"/>
        <m id="r24796644" t="d" c="31" ts="2509110454" ts-tts="25-09-11 04:54:13.949"/>
        <m id="r24796646" t="d" c="31" ts="2509110454" ts-tts="25-09-11 04:54:13.949"/>
    </dp>
</s>


<s id="-1448628132290741368-2509111335-13" eva="8000320">
    <ar ct="2509111425" l="RB58">
        <m id="r24863761" t="d" c="43" ts="2509111402" ts-tts="25-09-11 14:02:55.825"/>
        <m id="r24863763" t="d" c="43" ts="2509111402" ts-tts="25-09-11 14:02:55.825"/>
        <m id="r24863768" t="d" c="43" ts="2509111402" ts-tts="25-09-11 14:02:55.825"/>
    </ar>
</s>


<s id="7561757803291504796-2509111402-7" eva="8000320">
    <ar ct="2509111436" l="RB54">
        <m id="r24796553" t="f" c="1000" ts="2509110453" ts-tts="25-09-11 04:54:13.950"/>
        <m id="r24796669" t="d" c="31" ts="2509110454" ts-tts="25-09-11 04:54:13.950"/>
        <m id="r24796671" t="d" c="31" ts="2509110454" ts-tts="25-09-11 04:54:13.950"/>
        <m id="r24865159" t="d" c="45" ts="2509111412" ts-tts="25-09-11 14:13:10.688"/>
    </ar>
    <dp ct="2509111439" l="RB54">
        <m id="r24796553" t="f" c="1000" ts="2509110453" ts-tts="25-09-11 04:54:13.950"/>
        <m id="r24796669" t="d" c="31" ts="2509110454" ts-tts="25-09-11 04:54:13.950"/>
        <m id="r24796671" t="d" c="31" ts="2509110454" ts-tts="25-09-11 04:54:13.950"/>
        <m id="r24865159" t="d" c="45" ts="2509111412" ts-tts="25-09-11 14:13:10.688"/>
    </dp>
</s>


<s id="2236987104785968829-2509111437-1" eva="8000320">
    <dp ct="2509111437" l="RB58">
        <m id="r24865131" t="d" c="21" ts="2509111412" ts-tts="25-09-11 14:12:54.928"/>
    </dp>
</s>


<s id="-6358342590570712060-2509110712-20" eva="8000320">
    <m id="r2397244" t="h" from="2504021351" to="2509302359" cat="Information" ts="2504021355" ts-tts="25-09-10 23:16:04.280" pr="2"/>
    <m id="r2471136" t="h" from="2509010000" to="2509302300" cat="Information" ts="2508312308" ts-tts="25-09-10 23:16:04.464" pr="2"/>
    <m id="r2489613" t="h" from="2509110712" to="2509111542" cat="Information" ts="2509110420" ts-tts="25-09-11 04:20:23.226" pr="2"/>
    <m id="r2484847" t="h" from="2509011500" to="2509192359" cat="Information" ts="2509011714" ts-tts="25-09-10 23:16:04.684" pr="2"/>
    <m id="r2392382" t="h" from="2503250000" to="2512132359" cat="Information" ts="2503242304" ts-tts="25-09-10 23:16:04.280" pr="2"/>
    <m id="r2489491" t="h" from="2509102052" to="2509111500" cat="Information" ts="2509102101" ts-tts="25-09-10 23:16:04.795" pr="3"/>
    <ar ct="2509111444">
        <m id="r24795381" t="q" c="95" ts="2509110421" ts-tts="25-09-11 04:21:40.155"/>
        <m id="r24795383" t="q" c="95" ts="2509110421" ts-tts="25-09-11 04:21:40.155"/>
    </ar>
    <dp ct="2509111445">
        <m id="r24795381" t="q" c="95" ts="2509110421" ts-tts="25-09-11 04:21:40.155"/>
        <m id="r24795383" t="q" c="95" ts="2509110421" ts-tts="25-09-11 04:21:40.155"/>
    </dp>
</s>


<s id="-8278523531443108700-2509111355-3" eva="8000320">
    <ar ct="2509111434" l="RE5"/>
    <dp ct="2509111436" l="RE5"/>
</s>


<s id="7127840288788121534-2509111305-10" eva="8000320">
    <ar ct="2509111426" l="RE5"/>
    <dp ct="2509111429" l="RE5"/>
</s>


<s id="-2295331503101489009-2509111333-3" eva="8000320">
    <ar ct="2509111412"/>
    <dp ct="2509111413"/>
</s>


<s id="6913518424079486697-2509111332-9" eva="8000320">
    <ar ct="2509111425" l="44">
        <m id="r24849155" t="f" c="0" ts="2509111212" ts-tts="25-09-11 12:12:40.520"/>
    </ar>
</s>


<s id="-1378667911472082187-2509111126-16" eva="8000320">
    <ar ct="2509112012">
        <m id="r24864380" t="d" c="31" ts="2509111407" ts-tts="25-09-11 14:07:39.626"/>
        <m id="r24864382" t="d" c="31" ts="2509111407" ts-tts="25-09-11 14:07:39.626"/>
    </ar>
    <dp ct="2509112014">
        <m id="r24864380" t="d" c="31" ts="2509111407" ts-tts="25-09-11 14:07:39.626"/>
        <m id="r24864382" t="d" c="31" ts="2509111407" ts-tts="25-09-11 14:07:39.626"/>
    </dp>
</s>


<s id="-638968809069659586-2509111205-10" eva="8000320">
    <ar ct="2509111349" l="RE5">
        <m id="r24857275" t="f" c="1000" ts="2509111314" ts-tts="25-09-11 13:14:57.179"/>
        <m id="r24857277" t="d" c="38" ts="2509111314" ts-tts="25-09-11 13:14:57.179"/>
        <m id="r24857278" t="d" c="38" ts="2509111314" ts-tts="25-09-11 13:14:57.179"/>
        <m id="r24864016" t="d" c="45" ts="2509111405" ts-tts="25-09-11 14:05:17.816"/>
    </ar>
    <dp ct="2509111349" l="RE5">
        <m id="r24857275" t="f" c="1000" ts="2509111314" ts-tts="25-09-11 13:14:57.179"/>
        <m id="r24857277" t="d" c="38" ts="2509111314" ts-tts="25-09-11 13:14:57.179"/>
        <m id="r24857278" t="d" c="38" ts="2509111314" ts-tts="25-09-11 13:14:57.179"/>
        <m id="r24864016" t="d" c="45" ts="2509111405" ts-tts="25-09-11 14:05:17.816"/>
    </dp>
</s>


<s id="2979813652439599907-2509111042-19" eva="8000320">
    <m id="r2488123" t="h" from="2509080000" to="2512132359" cat="Information" ts="2509080956" ts-tts="25-09-10 23:16:04.767" pr="1"/>
    <m id="r2489813" t="h" from="2509110700" to="2509122359" cat="Großstörung" ts="2509111213" ts-tts="25-09-11 12:13:59.556" pr="1"/>
    <ar ct="2509111501"/>
    <dp ct="2509111503"/>
</s>


<s id="-8153059487835018416-2509111434-1" eva="8000320">
    <dp ct="2509111434" l="44"/>
</s>


<s id="9006451851335030111-2509111433-17" eva="8000320">
    <m id="r2488123" t="h" from="2509080000" to="2512132359" cat="Information" ts="2509080956" ts-tts="25-09-10 23:16:04.767" pr="1"/>
    <ar ct="2509111900"/>
    <dp ct="2509111902"/>
</s>


<s id="580136539271098796-2509120502-1" eva="8000320">
    <dp ct="2509120502" l="RB54">
        <m id="r24863314" t="f" c="1000" ts="2509111400" ts-tts="25-09-11 14:00:34.660"/>
        <m id="r24863551" t="d" c="31" ts="2509111400" ts-tts="25-09-11 14:00:34.660"/>
        <m id="r24863553" t="d" c="31" ts="2509111400" ts-tts="25-09-11 14:00:34.660"/>
    </dp>
</s>


<s id="4870413973009524025-2509120043-1" eva="8000320">
    <dp ct="2509120043" l="RB54">
        <m id="r24863311" t="f" c="1000" ts="2509111400" ts-tts="25-09-11 14:00:34.660"/>
        <m id="r24863513" t="d" c="31" ts="2509111400" ts-tts="25-09-11 14:00:34.660"/>
        <m id="r24863514" t="d" c="31" ts="2509111400" ts-tts="25-09-11 14:00:34.660"/>
    </dp>
</s>


<s id="77160974754847052-2509120509-12" eva="8000320">
    <ar ct="2509120551" l="RB58"/>
</s>


<s id="5782955865591927184-2509120537-1" eva="8000320">
    <dp ct="2509120537" l="RB58"/>
</s>


<s id="446037158408459292-2509120052-6" eva="8000320">
    <ar ct="2509120127" l="RB54"/>
</s>


<s id="1562629981270866322-2509120538-20" eva="8000320">
    <ar ct="2509120651" l="RB58"/>
</s>


<s id="-7419220671112678036-2509120532-12" eva="8000320">
    <ar ct="2509120623" l="RB58"/>
</s>


<s id="8055053294863528360-2509111428-11" eva="8000320">
    <ar ct="2509111524" l="44">
        <m id="r24849182" t="f" c="0" ts="2509111212" ts-tts="25-09-11 12:12:56.344"/>
        <m id="r24849183" t="f" c="0" ts="2509111212" ts-tts="25-09-11 12:12:56.344"/>
    </ar>
</s>


<s id="-1244506323428825924-2509110631-21" eva="8000320">
    <m id="r2489682" t="h" from="2509110631" to="2509111919" cat="Information" ts="2509110655" ts-tts="25-09-11 06:55:42.761" pr="2"/>
    <m id="r2489852" t="h" from="2509111411" to="2509111417" cat="Information" ts="2509111340" ts-tts="25-09-11 13:40:23.021" pr="2"/>
    <ar ct="2509111457">
        <m id="r24752173" t="f" c="0" ts="2509101758" ts-tts="25-09-10 17:58:59.905"/>
        <m id="r24754589" t="f" c="0" ts="2509101816" ts-tts="25-09-10 18:16:10.469"/>
        <m id="r24803976" t="q" c="90" ts="2509110630" ts-tts="25-09-11 06:30:27.339"/>
        <m id="r24803978" t="q" c="90" ts="2509110630" ts-tts="25-09-11 06:30:27.339"/>
        <m id="r24822359" t="d" c="43" ts="2509110902" ts-tts="25-09-11 09:02:17.248"/>
        <m id="r24822361" t="d" c="43" ts="2509110902" ts-tts="25-09-11 09:02:17.248"/>
        <m id="r24826621" t="f" c="0" ts="2509110932" ts-tts="25-09-11 09:32:04.214"/>
        <m id="r24827207" t="f" c="0" ts="2509110936" ts-tts="25-09-11 09:36:14.498"/>
        <m id="r24857526" t="f" c="0" ts="2509111316" ts-tts="25-09-11 13:17:02.876"/>
        <m id="r24860398" t="f" c="0" ts="2509111338" ts-tts="25-09-11 13:38:17.478"/>
        <m id="r24862206" t="f" c="0" ts="2509111352" ts-tts="25-09-11 13:52:26.668"/>
    </ar>
    <dp ct="2509111459">
        <m id="r24752173" t="f" c="0" ts="2509101758" ts-tts="25-09-10 17:58:59.905"/>
        <m id="r24754589" t="f" c="0" ts="2509101816" ts-tts="25-09-10 18:16:10.469"/>
        <m id="r24803976" t="q" c="90" ts="2509110630" ts-tts="25-09-11 06:30:27.339"/>
        <m id="r24803978" t="q" c="90" ts="2509110630" ts-tts="25-09-11 06:30:27.339"/>
        <m id="r24822359" t="d" c="43" ts="2509110902" ts-tts="25-09-11 09:02:17.248"/>
        <m id="r24822361" t="d" c="43" ts="2509110902" ts-tts="25-09-11 09:02:17.248"/>
        <m id="r24826621" t="f" c="0" ts="2509110932" ts-tts="25-09-11 09:32:04.214"/>
        <m id="r24827207" t="f" c="0" ts="2509110936" ts-tts="25-09-11 09:36:14.498"/>
        <m id="r24857526" t="f" c="0" ts="2509111316" ts-tts="25-09-11 13:17:02.876"/>
        <m id="r24860398" t="f" c="0" ts="2509111338" ts-tts="25-09-11 13:38:17.478"/>
        <m id="r24862206" t="f" c="0" ts="2509111352" ts-tts="25-09-11 13:52:26.668"/>
    </dp>
</s>


<s id="9042395260942796037-2509111419-12" eva="8000320">
    <m id="r2489813" t="h" from="2509110700" to="2509122359" cat="Großstörung" ts="2509111213" ts-tts="25-09-11 12:13:59.556" pr="1"/>
    <ar ct="2509111856"/>
    <dp ct="2509111857"/>
</s>


<s id="6687978122309741738-2509110821-12" eva="8000320">
    <m id="r2489851" t="h" from="2509110821" to="2509111719" cat="Information" ts="2509111333" ts-tts="25-09-11 13:33:34.593" pr="2"/>
    <m id="r2489813" t="h" from="2509110700" to="2509122359" cat="Großstörung" ts="2509111213" ts-tts="25-09-11 12:13:59.556" pr="1"/>
    <m id="r2489735" t="h" from="2509110910" to="2509111400" cat="Störung" ts="2509110927" ts-tts="25-09-11 13:16:05.139" pr="1"/>
    <m id="r990663648" t="c" ts="2509111332" ts-tts="25-09-11 13:32:15.664"/>
    <m id="r990663651" t="c" ts="2509111332" ts-tts="25-09-11 13:32:15.664"/>
    <m id="r990663652" t="c" ts="2509111332" ts-tts="25-09-11 13:32:15.664"/>
    <ar cpth="Frankfurt(Main)Hbf|Darmstadt Hbf|Bensheim|Weinheim(Bergstr)Hbf|Neu-Edingen/Friedrichsfeld|Stuttgart Hbf|Ulm Hbf|Günzburg|Augsburg Hbf|München Hbf|München Ost" ppth="Frankfurt(Main)Hbf|Darmstadt Hbf|Bensheim|Weinheim(Bergstr)Hbf|Heidelberg Hbf|Stuttgart Hbf|Ulm Hbf|Günzburg|Augsburg Hbf|München Hbf|München Ost" pp="4" ct="2509111347" pt="2509111253">
        <m id="r24822156" t="d" c="38" ts="2509110859" ts-tts="25-09-11 08:59:56.002"/>
        <m id="r24822158" t="d" c="38" ts="2509110859" ts-tts="25-09-11 08:59:56.002"/>
        <m id="r24824557" t="f" c="0" ts="2509110917" ts-tts="25-09-11 09:17:25.348"/>
        <m id="r24824711" t="f" c="0" ts="2509110918" ts-tts="25-09-11 09:18:12.310"/>
        <m id="r24826830" t="d" c="40" ts="2509110933" ts-tts="25-09-11 09:34:09.134"/>
        <m id="r24826832" t="d" c="40" ts="2509110933" ts-tts="25-09-11 09:34:09.134"/>
        <m id="r24826833" t="d" c="40" ts="2509110933" ts-tts="25-09-11 09:34:09.134"/>
        <m id="r24826835" t="d" c="40" ts="2509110933" ts-tts="25-09-11 09:34:09.134"/>
        <m id="r24826836" t="d" c="40" ts="2509110933" ts-tts="25-09-11 09:34:09.134"/>
        <m id="r24826838" t="d" c="40" ts="2509110933" ts-tts="25-09-11 09:34:09.134"/>
        <m id="r24826839" t="d" c="40" ts="2509110933" ts-tts="25-09-11 09:34:09.134"/>
        <m id="r24826841" t="d" c="40" ts="2509110933" ts-tts="25-09-11 09:34:09.134"/>
        <m id="r24826842" t="d" c="40" ts="2509110933" ts-tts="25-09-11 09:34:09.134"/>
        <m id="r24826844" t="d" c="40" ts="2509110933" ts-tts="25-09-11 09:34:09.134"/>
        <m id="r24830969" t="f" c="0" ts="2509111003" ts-tts="25-09-11 10:03:24.233"/>
        <m id="r24844767" t="f" c="0" ts="2509111137" ts-tts="25-09-11 11:38:05.103"/>
        <m id="r24856827" t="f" c="0" ts="2509111310" ts-tts="25-09-11 13:10:13.576"/>
        <m id="r24859802" t="q" c="95" ts="2509111333" ts-tts="25-09-11 13:33:18.992"/>
        <m id="r24859809" t="q" c="95" ts="2509111333" ts-tts="25-09-11 13:33:18.992"/>
    </ar>
    <dp cpth="Prien am Chiemsee|Traunstein|Freilassing|Salzburg Hbf|Golling-Abtenau|Bischofshofen|St. Johann im Pongau|Schwarzach-St.Veit|Dorfgastein|Bad Hofgastein|Bad Gastein|Mallnitz-Obervellach|Spittal-Millstättersee|Villach Hbf|Velden am Wörther See|Pörtschach am Wörther See|Krumpendorf/Wörthersee|Klagenfurt Hbf" ppth="Prien am Chiemsee|Traunstein|Freilassing|Salzburg Hbf|Golling-Abtenau|Bischofshofen|St. Johann im Pongau|Schwarzach-St.Veit|Dorfgastein|Bad Hofgastein|Bad Gastein|Mallnitz-Obervellach|Spittal-Millstättersee|Villach Hbf|Velden am Wörther See|Pörtschach am Wörther See|Krumpendorf/Wörthersee|Klagenfurt Hbf" pp="4" ct="2509111348" pt="2509111254">
        <m id="r24822156" t="d" c="38" ts="2509110859" ts-tts="25-09-11 08:59:56.002"/>
        <m id="r24822158" t="d" c="38" ts="2509110859" ts-tts="25-09-11 08:59:56.002"/>
        <m id="r24824557" t="f" c="0" ts="2509110917" ts-tts="25-09-11 09:17:25.348"/>
        <m id="r24824711" t="f" c="0" ts="2509110918" ts-tts="25-09-11 09:18:12.310"/>
        <m id="r24826830" t="d" c="40" ts="2509110933" ts-tts="25-09-11 09:34:09.134"/>
        <m id="r24826832" t="d" c="40" ts="2509110933" ts-tts="25-09-11 09:34:09.134"/>
        <m id="r24826833" t="d" c="40" ts="2509110933" ts-tts="25-09-11 09:34:09.134"/>
        <m id="r24826835" t="d" c="40" ts="2509110933" ts-tts="25-09-11 09:34:09.134"/>
        <m id="r24826836" t="d" c="40" ts="2509110933" ts-tts="25-09-11 09:34:09.134"/>
        <m id="r24826838" t="d" c="40" ts="2509110933" ts-tts="25-09-11 09:34:09.134"/>
        <m id="r24826839" t="d" c="40" ts="2509110933" ts-tts="25-09-11 09:34:09.134"/>
        <m id="r24826841" t="d" c="40" ts="2509110933" ts-tts="25-09-11 09:34:09.134"/>
        <m id="r24826842" t="d" c="40" ts="2509110933" ts-tts="25-09-11 09:34:09.134"/>
        <m id="r24826844" t="d" c="40" ts="2509110933" ts-tts="25-09-11 09:34:09.134"/>
        <m id="r24830969" t="f" c="0" ts="2509111003" ts-tts="25-09-11 10:03:24.233"/>
        <m id="r24844767" t="f" c="0" ts="2509111137" ts-tts="25-09-11 11:38:05.103"/>
        <m id="r24856827" t="f" c="0" ts="2509111310" ts-tts="25-09-11 13:10:13.576"/>
        <m id="r24859802" t="q" c="95" ts="2509111333" ts-tts="25-09-11 13:33:18.992"/>
        <m id="r24859809" t="q" c="95" ts="2509111333" ts-tts="25-09-11 13:33:18.992"/>
    </dp>
    <tl f="F" t="p" o="80" c="EC" n="113"/>
</s>


<s id="-775848972267492664-2509111340-1" eva="8000320">
    <dp ct="2509111340" l="RB58"/>
</s>


<s id="7909461491736065006-2509111008-10" eva="8000320">
    <ar cp="2" ct="2509111340">
        <m id="r24785303" t="f" c="1000" ts="2509102310" ts-tts="25-09-10 23:10:57.088"/>
        <m id="r24785432" t="f" c="0" ts="2509102312" ts-tts="25-09-10 23:12:45.718"/>
        <m id="r24785433" t="f" c="0" ts="2509102312" ts-tts="25-09-10 23:12:45.718"/>
    </ar>
    <dp cp="2" ct="2509111339">
        <m id="r24785303" t="f" c="1000" ts="2509102310" ts-tts="25-09-10 23:10:57.088"/>
        <m id="r24785432" t="f" c="0" ts="2509102312" ts-tts="25-09-10 23:12:45.718"/>
        <m id="r24785433" t="f" c="0" ts="2509102312" ts-tts="25-09-10 23:12:45.718"/>
    </dp>
</s>


<s id="1609183973817032683-2509111255-3" eva="8000320">
    <ar ct="2509111338" l="RE5">
        <m id="r24857366" t="d" c="38" ts="2509111315" ts-tts="25-09-11 13:15:44.235"/>
    </ar>
    <dp ct="2509111339" l="RE5">
        <m id="r24857366" t="d" c="38" ts="2509111315" ts-tts="25-09-11 13:15:44.235"/>
    </dp>
</s>


<s id="4410555567647297858-2509111243-7" eva="8000320">
    <ar ct="2509111334" l="RB54">
        <m id="r24796533" t="f" c="1000" ts="2509110453" ts-tts="25-09-11 04:54:13.949"/>
        <m id="r24796617" t="d" c="31" ts="2509110453" ts-tts="25-09-11 04:54:13.949"/>
        <m id="r24796618" t="d" c="31" ts="2509110454" ts-tts="25-09-11 04:54:13.949"/>
        <m id="r24796622" t="d" c="31" ts="2509110454" ts-tts="25-09-11 04:54:13.949"/>
        <m id="r24857422" t="d" c="38" ts="2509111316" ts-tts="25-09-11 13:16:15.643"/>
    </ar>
    <dp ct="2509111336" l="RB54">
        <m id="r24796533" t="f" c="1000" ts="2509110453" ts-tts="25-09-11 04:54:13.949"/>
        <m id="r24796617" t="d" c="31" ts="2509110453" ts-tts="25-09-11 04:54:13.949"/>
        <m id="r24796618" t="d" c="31" ts="2509110454" ts-tts="25-09-11 04:54:13.949"/>
        <m id="r24796622" t="d" c="31" ts="2509110454" ts-tts="25-09-11 04:54:13.949"/>
        <m id="r24857422" t="d" c="38" ts="2509111316" ts-tts="25-09-11 13:16:15.643"/>
        <m id="r24859600" t="f" c="0" ts="2509111332" ts-tts="25-09-11 13:32:15.828"/>
    </dp>
</s>


<s id="-665242477085170679-2509111334-1" eva="8000320">
    <dp ct="2509111335" l="44">
        <m id="r24859597" t="f" c="0" ts="2509111332" ts-tts="25-09-11 13:32:15.826"/>
    </dp>
</s>


<s id="-5392147654592648113-2509111302-7" eva="8000320">
    <ar ct="2509111330" l="RB54">
        <m id="r24796541" t="f" c="1000" ts="2509110453" ts-tts="25-09-11 04:54:13.950"/>
        <m id="r24796616" t="d" c="31" ts="2509110453" ts-tts="25-09-11 04:54:13.950"/>
    </ar>
    <dp ct="2509111333" l="RB54">
        <m id="r24796541" t="f" c="1000" ts="2509110453" ts-tts="25-09-11 04:54:13.950"/>
        <m id="r24796616" t="d" c="31" ts="2509110453" ts-tts="25-09-11 04:54:13.950"/>
    </dp>
</s>


<s id="3937160835124640915-2509111135-15" eva="8000320">
    <ar ct="2509111747">
        <m id="r24859445" t="d" c="24" ts="2509111331" ts-tts="25-09-11 13:31:12.772"/>
        <m id="r24859447" t="d" c="24" ts="2509111331" ts-tts="25-09-11 13:31:12.772"/>
        <m id="r24859449" t="d" c="24" ts="2509111331" ts-tts="25-09-11 13:31:12.772"/>
    </ar>
    <dp ct="2509111749">
        <m id="r24859445" t="d" c="24" ts="2509111331" ts-tts="25-09-11 13:31:12.772"/>
        <m id="r24859447" t="d" c="24" ts="2509111331" ts-tts="25-09-11 13:31:12.772"/>
        <m id="r24859449" t="d" c="24" ts="2509111331" ts-tts="25-09-11 13:31:12.772"/>
    </dp>
</s>


<s id="-7004640484950825935-2509111303-1" eva="8000320">
    <dp ct="2509111305" l="RB58">
        <m id="r24856520" t="d" c="43" ts="2509111307" ts-tts="25-09-11 13:07:35.954"/>
        <m id="r24859595" t="f" c="0" ts="2509111332" ts-tts="25-09-11 13:32:15.825"/>
    </dp>
</s>


<s id="5620190010677322930-2509111237-13" eva="8000320">
    <ar ct="2509111328" l="RB58">
        <m id="r24857186" t="d" c="48" ts="2509111313" ts-tts="25-09-11 13:13:54.223"/>
        <m id="r24858727" t="d" c="44" ts="2509111323" ts-tts="25-09-11 13:23:52.379"/>
    </ar>
</s>


<s id="-1635910124413663959-2509111137-16" eva="8000320">
    <ar ct="2509111325" l="44">
        <m id="r24844075" t="d" c="21" ts="2509111133" ts-tts="25-09-11 11:34:09.460"/>
        <m id="r24844077" t="d" c="21" ts="2509111133" ts-tts="25-09-11 11:34:09.460"/>
    </ar>
</s>


<s id="287494478792440265-2509111533-3" eva="8000320">
    <ar cpth="München Ost">
        <m id="r24858326" t="f" c="0" ts="2509111320" ts-tts="25-09-11 13:20:58.891"/>
    </ar>
    <dp cpth="Kufstein|Wörgl Hbf|Jenbach|Innsbruck Hbf|Brennero/Brenner|Bressanone/Brixen|Bolzano/Bozen|Trento|Rovereto|Verona Porta Nuova|Bologna Centrale">
        <m id="r24858326" t="f" c="0" ts="2509111320" ts-tts="25-09-11 13:20:58.891"/>
    </dp>
</s>


<s id="8787741641562669233-2509110745-12" eva="8000320">
    <ar cpth="Bologna Centrale|Verona Porta Nuova|Rovereto|Trento|Bolzano/Bozen|Bressanone/Brixen|Brennero/Brenner|Innsbruck Hbf|Jenbach|Wörgl Hbf|Kufstein" ppth="Bologna Centrale|Verona Porta Nuova|Rovereto|Trento|Bolzano/Bozen|Bressanone/Brixen|Brennero/Brenner|Innsbruck Hbf|Jenbach|Wörgl Hbf|Kufstein" pp="3" ct="2509111435" pt="2509111345">
        <m id="r24853782" t="d" c="24" ts="2509111244" ts-tts="25-09-11 12:44:45.001"/>
        <m id="r24853784" t="d" c="24" ts="2509111244" ts-tts="25-09-11 12:44:45.001"/>
        <m id="r24853786" t="d" c="24" ts="2509111244" ts-tts="25-09-11 12:44:45.001"/>
        <m id="r24853788" t="d" c="24" ts="2509111244" ts-tts="25-09-11 12:44:45.001"/>
        <m id="r24856573" t="f" c="0" ts="2509111307" ts-tts="25-09-11 13:07:51.631"/>
        <m id="r24858258" t="f" c="0" ts="2509111320" ts-tts="25-09-11 13:20:27.285"/>
    </ar>
    <dp cpth="München Ost" ppth="München Ost|München Hbf Gl.5-10" pp="3" ct="2509111436" pt="2509111346">
        <m id="r24853782" t="d" c="24" ts="2509111244" ts-tts="25-09-11 12:44:45.002"/>
        <m id="r24853784" t="d" c="24" ts="2509111244" ts-tts="25-09-11 12:44:45.002"/>
        <m id="r24853786" t="d" c="24" ts="2509111244" ts-tts="25-09-11 12:44:45.002"/>
        <m id="r24853788" t="d" c="24" ts="2509111244" ts-tts="25-09-11 12:44:45.002"/>
        <m id="r24856573" t="f" c="0" ts="2509111307" ts-tts="25-09-11 13:07:51.631"/>
        <m id="r24858258" t="f" c="0" ts="2509111320" ts-tts="25-09-11 13:20:27.285"/>
    </dp>
    <tl t="p" o="80" c="RJ" n="88"/>
</s>


<s id="-940035628142522529-2509110842-19" eva="8000320">
    <m id="r2488123" t="h" from="2509080000" to="2512132359" cat="Information" ts="2509080956" ts-tts="25-09-10 23:16:04.767" pr="1"/>
    <ar ct="2509111315">
        <m id="r24850381" t="d" c="67" ts="2509111219" ts-tts="25-09-11 12:20:04.230"/>
        <m id="r24850383" t="d" c="67" ts="2509111219" ts-tts="25-09-11 12:20:04.230"/>
        <m id="r24850577" t="f" c="0" ts="2509111221" ts-tts="25-09-11 12:21:22.967"/>
    </ar>
    <dp ct="2509111316">
        <m id="r24850381" t="d" c="67" ts="2509111219" ts-tts="25-09-11 12:20:04.230"/>
        <m id="r24850383" t="d" c="67" ts="2509111219" ts-tts="25-09-11 12:20:04.230"/>
        <m id="r24850577" t="f" c="0" ts="2509111221" ts-tts="25-09-11 12:21:22.967"/>
    </dp>
</s>


<s id="7065259282760334107-2509111219-12" eva="8000320">
    <m id="r2489813" t="h" from="2509110700" to="2509122359" cat="Großstörung" ts="2509111213" ts-tts="25-09-11 12:13:59.556" pr="1"/>
    <m id="r2489735" t="h" from="2509110910" to="2509111400" cat="Störung" ts="2509110927" ts-tts="25-09-11 13:16:05.139" pr="1"/>
    <ar cpth="Frankfurt(Main)Hbf|Darmstadt Hbf|Bensheim|Weinheim(Bergstr)Hbf|Stuttgart Hbf|Ulm Hbf|Günzburg|Augsburg Hbf|München Hbf|München Ost" ct="2509111656">
        <m id="r24852999" t="f" c="0" ts="2509111238" ts-tts="25-09-11 12:38:42.428"/>
        <m id="r24853000" t="f" c="0" ts="2509111238" ts-tts="25-09-11 12:38:42.428"/>
        <m id="r24853302" t="d" c="40" ts="2509111241" ts-tts="25-09-11 12:41:51.791"/>
        <m id="r24853304" t="d" c="40" ts="2509111241" ts-tts="25-09-11 12:41:51.791"/>
    </ar>
    <dp cpth="Prien am Chiemsee|Traunstein|Freilassing|Salzburg Hbf|Salzburg Süd|Hallein|Golling-Abtenau|Werfen|Bischofshofen" ct="2509111657">
        <m id="r24852999" t="f" c="0" ts="2509111238" ts-tts="25-09-11 12:38:42.428"/>
        <m id="r24853000" t="f" c="0" ts="2509111238" ts-tts="25-09-11 12:38:42.428"/>
        <m id="r24853302" t="d" c="40" ts="2509111241" ts-tts="25-09-11 12:41:51.791"/>
        <m id="r24853304" t="d" c="40" ts="2509111241" ts-tts="25-09-11 12:41:51.791"/>
    </dp>
</s>


<s id="-9206844568518319678-2509110800-5" eva="8000320">
    <m id="r2488123" t="h" from="2509080000" to="2512132359" cat="Information" ts="2509080956" ts-tts="25-09-10 23:16:04.767" pr="1"/>
    <m id="r2489813" t="h" from="2509110700" to="2509122359" cat="Großstörung" ts="2509111213" ts-tts="25-09-11 12:13:59.556" pr="1"/>
    <m id="r2489735" t="h" from="2509110910" to="2509111400" cat="Störung" ts="2509110927" ts-tts="25-09-11 13:16:05.139" pr="1"/>
    <ar cpth="Salzburg Hbf|Freilassing|Traunstein|Prien am Chiemsee" ct="2509110859"/>
    <dp cpth="München Ost|München Hbf|Augsburg Hbf|Günzburg|Ulm Hbf|Stuttgart Hbf|Weinheim(Bergstr)Hbf|Bensheim|Darmstadt Hbf|Frankfurt(Main)Hbf" ct="2509110902"/>
</s>


<s id="9084265654909040416-2509110543-6" eva="8000320">
    <m id="r2488123" t="h" from="2509080000" to="2512132359" cat="Information" ts="2509080956" ts-tts="25-09-10 23:16:04.767" pr="1"/>
    <m id="r2489735" t="h" from="2509110910" to="2509111400" cat="Störung" ts="2509110927" ts-tts="25-09-11 13:16:05.139" pr="1"/>
    <ar cpth="Salzburg Hbf|Freilassing|Traunstein|Prien am Chiemsee|Bad Endorf" ct="2509110645">
        <m id="r24800720" t="f" c="1000" ts="2509110555" ts-tts="25-09-11 05:55:25.735"/>
        <m id="r24800721" t="f" c="0" ts="2509110555" ts-tts="25-09-11 05:55:25.735"/>
        <m id="r24800722" t="f" c="0" ts="2509110555" ts-tts="25-09-11 05:55:25.735"/>
        <m id="r24800759" t="f" c="0" ts="2509110555" ts-tts="25-09-11 05:55:56.710"/>
        <m id="r24800761" t="f" c="0" ts="2509110555" ts-tts="25-09-11 05:55:56.710"/>
    </ar>
    <dp cpth="München Ost|München Hbf|Augsburg Hbf|Günzburg|Ulm Hbf|Stuttgart Hbf|Weinheim(Bergstr)Hbf|Bensheim|Darmstadt Hbf|Frankfurt(Main)Hbf" ct="2509110649">
        <m id="r24800720" t="f" c="1000" ts="2509110555" ts-tts="25-09-11 05:55:25.735"/>
        <m id="r24800721" t="f" c="0" ts="2509110555" ts-tts="25-09-11 05:55:25.735"/>
        <m id="r24800722" t="f" c="0" ts="2509110555" ts-tts="25-09-11 05:55:25.735"/>
        <m id="r24800759" t="f" c="0" ts="2509110555" ts-tts="25-09-11 05:55:56.710"/>
        <m id="r24800761" t="f" c="0" ts="2509110555" ts-tts="25-09-11 05:55:56.710"/>
    </dp>
</s>


<s id="5279283621341660290-2509120551-2" eva="8000320">
    <ar ct="2509120701">
        <m id="r24844417" t="d" c="31" ts="2509111135" ts-tts="25-09-11 11:35:59.604"/>
        <m id="r24844419" t="d" c="31" ts="2509111135" ts-tts="25-09-11 11:35:59.604"/>
        <m id="r24844420" t="d" c="31" ts="2509111135" ts-tts="25-09-11 11:35:59.604"/>
        <m id="r24844422" t="d" c="31" ts="2509111135" ts-tts="25-09-11 11:35:59.604"/>
        <m id="r24844423" t="d" c="31" ts="2509111135" ts-tts="25-09-11 11:35:59.604"/>
        <m id="r24844425" t="d" c="31" ts="2509111135" ts-tts="25-09-11 11:35:59.604"/>
        <m id="r24844426" t="d" c="31" ts="2509111135" ts-tts="25-09-11 11:35:59.604"/>
        <m id="r24844428" t="d" c="31" ts="2509111135" ts-tts="25-09-11 11:35:59.604"/>
    </ar>
    <dp ct="2509120703">
        <m id="r24844417" t="d" c="31" ts="2509111135" ts-tts="25-09-11 11:35:59.604"/>
        <m id="r24844419" t="d" c="31" ts="2509111135" ts-tts="25-09-11 11:35:59.604"/>
        <m id="r24844420" t="d" c="31" ts="2509111135" ts-tts="25-09-11 11:35:59.604"/>
        <m id="r24844422" t="d" c="31" ts="2509111135" ts-tts="25-09-11 11:35:59.604"/>
        <m id="r24844423" t="d" c="31" ts="2509111135" ts-tts="25-09-11 11:35:59.604"/>
        <m id="r24844425" t="d" c="31" ts="2509111135" ts-tts="25-09-11 11:35:59.604"/>
        <m id="r24844426" t="d" c="31" ts="2509111135" ts-tts="25-09-11 11:35:59.604"/>
        <m id="r24844428" t="d" c="31" ts="2509111135" ts-tts="25-09-11 11:35:59.604"/>
    </dp>
</s>


<s id="-2638423983741105495-2509110952-12" eva="8000320">
    <ar ppth="Bologna Centrale|Verona Porta Nuova|Rovereto|Trento|Bolzano/Bozen|Bressanone/Brixen|Brennero/Brenner|Innsbruck Hbf|Jenbach|Wörgl Hbf|Kufstein" pp="3" ct="2509111635" pt="2509111545">
        <m id="r24834567" t="d" c="24" ts="2509111033" ts-tts="25-09-11 10:33:25.212"/>
        <m id="r24834569" t="d" c="24" ts="2509111033" ts-tts="25-09-11 10:33:25.212"/>
        <m id="r24856603" t="f" c="0" ts="2509111307" ts-tts="25-09-11 13:08:07.349"/>
    </ar>
    <dp ppth="München Ost|München Hbf" pp="3" ct="2509111636" pt="2509111546">
        <m id="r24834567" t="d" c="24" ts="2509111033" ts-tts="25-09-11 10:33:25.212"/>
        <m id="r24834569" t="d" c="24" ts="2509111033" ts-tts="25-09-11 10:33:25.212"/>
        <m id="r24856603" t="f" c="0" ts="2509111307" ts-tts="25-09-11 13:08:07.349"/>
    </dp>
    <tl t="p" o="80" c="RJ" n="86"/>
</s>


<s id="656052606331099139-2509111159-13" eva="8000320">
    <ar ct="2509111251" l="RB58">
        <m id="r24850781" t="f" c="1000" ts="2509111224" ts-tts="25-09-11 12:24:15.873"/>
        <m id="r24850782" t="d" c="38" ts="2509111224" ts-tts="25-09-11 12:24:15.873"/>
        <m id="r24850783" t="d" c="38" ts="2509111224" ts-tts="25-09-11 12:24:15.873"/>
    </ar>
</s>


<s id="-3031925877358690214-2509111620-12" eva="8000320">
    <m id="r2489813" t="h" from="2509110700" to="2509122359" cat="Großstörung" ts="2509111213" ts-tts="25-09-11 12:13:59.556" pr="1"/>
    <m id="r2489823" t="h" from="2509110857" to="2509112202" cat="Information" ts="2509111242" ts-tts="25-09-11 12:42:07.331" pr="2"/>
    <ar>
        <m id="r24853469" t="q" c="95" ts="2509111242" ts-tts="25-09-11 12:42:39.045"/>
    </ar>
    <dp>
        <m id="r24853469" t="q" c="95" ts="2509111242" ts-tts="25-09-11 12:42:39.045"/>
    </dp>
</s>


<s id="4339914957617149277-2509110857-10" eva="8000320">
    <m id="r2488123" t="h" from="2509080000" to="2512132359" cat="Information" ts="2509080956" ts-tts="25-09-10 23:16:04.767" pr="1"/>
    <m id="r2489813" t="h" from="2509110700" to="2509122359" cat="Großstörung" ts="2509111213" ts-tts="25-09-11 12:13:59.556" pr="1"/>
    <m id="r2489823" t="h" from="2509110857" to="2509112202" cat="Information" ts="2509111242" ts-tts="25-09-11 12:42:07.331" pr="2"/>
    <ar ct="2509111109">
        <m id="r24829495" t="q" c="86" ts="2509110951" ts-tts="25-09-11 09:51:54.531"/>
        <m id="r24835659" t="d" c="38" ts="2509111040" ts-tts="25-09-11 10:40:44.716"/>
    </ar>
    <dp ct="2509111110">
        <m id="r24829495" t="q" c="86" ts="2509110951" ts-tts="25-09-11 09:51:54.531"/>
        <m id="r24835659" t="d" c="38" ts="2509111040" ts-tts="25-09-11 10:40:44.716"/>
    </dp>
</s>


<s id="-2593623786603281392-2509111237-1" eva="8000320">
    <dp ct="2509111238" l="RB58"/>
</s>


<s id="-1044432761777850886-2509111155-3" eva="8000320">
    <ar ct="2509111236" l="RE5"/>
    <dp ct="2509111238" l="RE5"/>
</s>


<s id="6202821271617672866-2509111202-7" eva="8000320">
    <ar ct="2509111232" l="RB54">
        <m id="r24796547" t="f" c="1000" ts="2509110453" ts-tts="25-09-11 04:54:13.950"/>
        <m id="r24796624" t="d" c="31" ts="2509110454" ts-tts="25-09-11 04:54:13.950"/>
        <m id="r24796626" t="d" c="31" ts="2509110454" ts-tts="25-09-11 04:54:13.950"/>
    </ar>
    <dp ct="2509111236" l="RB54">
        <m id="r24796547" t="f" c="1000" ts="2509110453" ts-tts="25-09-11 04:54:13.950"/>
        <m id="r24796624" t="d" c="31" ts="2509110454" ts-tts="25-09-11 04:54:13.950"/>
        <m id="r24796626" t="d" c="31" ts="2509110454" ts-tts="25-09-11 04:54:13.950"/>
    </dp>
</s>


<s id="5880798641066714490-2509111234-1" eva="8000320">
    <dp ct="2509111235" l="44"/>
</s>


<s id="-8641835014411183854-2509111141-7" eva="8000320">
    <ar ct="2509111229" l="RB54">
        <m id="r24796544" t="f" c="1000" ts="2509110453" ts-tts="25-09-11 04:54:13.949"/>
        <m id="r24796623" t="d" c="31" ts="2509110454" ts-tts="25-09-11 04:54:13.949"/>
        <m id="r24849669" t="f" c="1000" ts="2509111215" ts-tts="25-09-11 12:15:19.171"/>
        <m id="r24849710" t="d" c="43" ts="2509111215" ts-tts="25-09-11 12:15:19.171"/>
        <m id="r24850510" t="d" c="21" ts="2509111220" ts-tts="25-09-11 12:20:35.713"/>
        <m id="r24850620" t="d" c="32" ts="2509111222" ts-tts="25-09-11 12:22:09.987"/>
    </ar>
    <dp ct="2509111235" l="RB54">
        <m id="r24796544" t="f" c="1000" ts="2509110453" ts-tts="25-09-11 04:54:13.949"/>
        <m id="r24796623" t="d" c="31" ts="2509110454" ts-tts="25-09-11 04:54:13.949"/>
        <m id="r24849669" t="f" c="1000" ts="2509111215" ts-tts="25-09-11 12:15:19.171"/>
        <m id="r24849710" t="d" c="43" ts="2509111215" ts-tts="25-09-11 12:15:19.171"/>
        <m id="r24850510" t="d" c="21" ts="2509111220" ts-tts="25-09-11 12:20:35.713"/>
        <m id="r24850620" t="d" c="32" ts="2509111222" ts-tts="25-09-11 12:22:09.987"/>
    </dp>
</s>


<s id="-7424620873862544327-2509111145-3" eva="8000320">
    <ar ct="2509111232">
        <m id="r24785506" t="f" c="1000" ts="2509102313" ts-tts="25-09-10 23:13:32.422"/>
        <m id="r24785511" t="f" c="0" ts="2509102313" ts-tts="25-09-10 23:13:32.422"/>
        <m id="r24785512" t="f" c="0" ts="2509102313" ts-tts="25-09-10 23:13:32.422"/>
    </ar>
    <dp ct="2509111233">
        <m id="r24785506" t="f" c="1000" ts="2509102313" ts-tts="25-09-10 23:13:32.422"/>
        <m id="r24785511" t="f" c="0" ts="2509102313" ts-tts="25-09-10 23:13:32.422"/>
        <m id="r24785512" t="f" c="0" ts="2509102313" ts-tts="25-09-10 23:13:32.422"/>
    </dp>
</s>


<s id="-4982883780120927371-2509111108-10" eva="8000320">
    <ar ct="2509111232" l="RE5">
        <m id="r24847951" t="f" c="1000" ts="2509111201" ts-tts="25-09-11 12:02:10.738"/>
        <m id="r24848001" t="d" c="38" ts="2509111202" ts-tts="25-09-11 12:02:42.218"/>
    </ar>
    <dp ct="2509111233" l="RE5">
        <m id="r24847951" t="f" c="1000" ts="2509111201" ts-tts="25-09-11 12:02:10.738"/>
        <m id="r24848001" t="d" c="38" ts="2509111202" ts-tts="25-09-11 12:02:42.218"/>
    </dp>
</s>


<s id="3476617309332154819-2509111132-9" eva="8000320">
    <ar ct="2509111227" l="44"/>
</s>


<s id="-4567135275624807105-2509111130-19" eva="8000320">
    <ar ct="2509111947"/>
    <dp ct="2509111949"/>
</s>


<s id="5717089827599043690-2509111137-13" eva="8000320">
    <ar ct="2509111219" l="RB58"/>
</s>


<s id="1131371632334260525-2509111132-3" eva="8000320">
    <ar ct="2509111212"/>
    <dp ct="2509111215"/>
</s>


<s id="-7911753228633891317-2509112134-1" eva="8000320">
    <dp l="44">
        <m id="r24849547" t="f" c="0" ts="2509111214" ts-tts="25-09-11 12:14:31.765"/>
    </dp>
</s>


<s id="8552451706123348592-2509111934-1" eva="8000320">
    <dp l="44">
        <m id="r24849362" t="f" c="0" ts="2509111213" ts-tts="25-09-11 12:13:59.845"/>
    </dp>
</s>


<s id="-467885100611588435-2509111457-10" eva="8000320">
    <m id="r2488123" t="h" from="2509080000" to="2512132359" cat="Information" ts="2509080956" ts-tts="25-09-10 23:16:04.767" pr="1"/>
    <m id="r2489813" t="h" from="2509110700" to="2509122359" cat="Großstörung" ts="2509111213" ts-tts="25-09-11 12:13:59.556" pr="1"/>
</s>


<s id="7828215980503160535-2509110816-3" eva="8000320">
    <m id="r2489813" t="h" from="2509110700" to="2509122359" cat="Großstörung" ts="2509111213" ts-tts="25-09-11 12:13:59.556" pr="1"/>
    <ar ct="2509110856">
        <m id="r24815661" t="q" c="98" ts="2509110806" ts-tts="25-09-11 08:06:27.826"/>
        <m id="r24815663" t="q" c="98" ts="2509110806" ts-tts="25-09-11 08:06:27.826"/>
    </ar>
    <dp ct="2509110858">
        <m id="r24815661" t="q" c="98" ts="2509110806" ts-tts="25-09-11 08:06:27.826"/>
        <m id="r24815663" t="q" c="98" ts="2509110806" ts-tts="25-09-11 08:06:27.826"/>
    </dp>
</s>


<s id="6164210511652592480-2509111642-19" eva="8000320">
    <m id="r2488123" t="h" from="2509080000" to="2512132359" cat="Information" ts="2509080956" ts-tts="25-09-10 23:16:04.767" pr="1"/>
    <m id="r2489813" t="h" from="2509110700" to="2509122359" cat="Großstörung" ts="2509111213" ts-tts="25-09-11 12:13:59.556" pr="1"/>
</s>


<s id="3864108912931363336-2509111734-1" eva="8000320">
    <dp l="44">
        <m id="r24849339" t="f" c="0" ts="2509111213" ts-tts="25-09-11 12:13:43.968"/>
    </dp>
</s>


<s id="1377954440643431132-2509112134-9" eva="8000320">
    <ar l="44">
        <m id="r24849332" t="f" c="0" ts="2509111213" ts-tts="25-09-11 12:13:43.968"/>
        <m id="r24849333" t="f" c="0" ts="2509111213" ts-tts="25-09-11 12:13:43.968"/>
    </ar>
</s>


<s id="4921052768424035588-2509111532-9" eva="8000320">
    <ar l="44">
        <m id="r24849258" t="f" c="0" ts="2509111213" ts-tts="25-09-11 12:13:12.162"/>
    </ar>
</s>


<s id="3090915631380043641-2509110808-10" eva="8000320">
    <ar cp="2" ct="2509111154">
        <m id="r24785277" t="f" c="1000" ts="2509102310" ts-tts="25-09-10 23:10:26.061"/>
        <m id="r24785371" t="f" c="0" ts="2509102312" ts-tts="25-09-10 23:12:14.595"/>
        <m id="r24785372" t="f" c="0" ts="2509102312" ts-tts="25-09-10 23:12:14.595"/>
    </ar>
    <dp cp="2" ct="2509111155">
        <m id="r24785277" t="f" c="1000" ts="2509102310" ts-tts="25-09-10 23:10:26.061"/>
        <m id="r24785371" t="f" c="0" ts="2509102312" ts-tts="25-09-10 23:12:14.595"/>
        <m id="r24785372" t="f" c="0" ts="2509102312" ts-tts="25-09-10 23:12:14.595"/>
    </dp>
</s>


<s id="-6377201694517348157-2509111055-3" eva="8000320">
    <ar ct="2509111133" l="RE5">
        <m id="r24847094" t="d" c="43" ts="2509111154" ts-tts="25-09-11 11:54:51.566"/>
    </ar>
    <dp ct="2509111137" l="RE5">
        <m id="r24847094" t="d" c="43" ts="2509111154" ts-tts="25-09-11 11:54:51.566"/>
    </dp>
</s>


<s id="3313346331866621575-2509111042-5" eva="8000320">
    <ar ct="2509111148"/>
    <dp ct="2509111150"/>
</s>


<s id="4851039227817789692-2509111144-1" eva="8000320">
    <dp ct="2509111144" l="RB58"/>
</s>


<s id="5224160355597006733-2509111102-7" eva="8000320">
    <ar ct="2509111133" l="RB54">
        <m id="r24796551" t="f" c="1000" ts="2509110453" ts-tts="25-09-11 04:54:13.950"/>
        <m id="r24796632" t="d" c="31" ts="2509110454" ts-tts="25-09-11 04:54:13.950"/>
    </ar>
    <dp ct="2509111135" l="RB54">
        <m id="r24796551" t="f" c="1000" ts="2509110453" ts-tts="25-09-11 04:54:13.950"/>
        <m id="r24796632" t="d" c="31" ts="2509110454" ts-tts="25-09-11 04:54:13.950"/>
    </dp>
</s>


<s id="8663039687891764241-2509111134-1" eva="8000320">
    <dp ct="2509111134" l="44"/>
</s>


<s id="-5099201580373839389-2509111043-7" eva="8000320">
    <ar ct="2509111129" l="RB54">
        <m id="r24796531" t="f" c="1000" ts="2509110453" ts-tts="25-09-11 04:54:13.949"/>
        <m id="r24796660" t="d" c="31" ts="2509110454" ts-tts="25-09-11 04:54:13.949"/>
        <m id="r24796665" t="d" c="31" ts="2509110454" ts-tts="25-09-11 04:54:13.949"/>
    </ar>
    <dp ct="2509111134" l="RB54">
        <m id="r24796531" t="f" c="1000" ts="2509110453" ts-tts="25-09-11 04:54:13.949"/>
        <m id="r24796660" t="d" c="31" ts="2509110454" ts-tts="25-09-11 04:54:13.949"/>
        <m id="r24796665" t="d" c="31" ts="2509110454" ts-tts="25-09-11 04:54:13.949"/>
    </dp>
</s>


<s id="2460523068896949477-2509111005-10" eva="8000320">
    <ar ct="2509111129" l="RE5"/>
    <dp ct="2509111130" l="RE5"/>
</s>


<s id="6992012378128167215-2509111956-10" eva="8000320">
    <ar ct="2509120804"/>
    <dp ct="2509120806"/>
</s>


<s id="-3823254010841261196-2509111900-10" eva="8000320">
    <ar ct="2509120804"/>
    <dp ct="2509120806"/>
</s>


<s id="-8677182982400525824-2509112046-5" eva="8000320">
    <ar ct="2509112155"/>
    <dp ct="2509112159"/>
</s>


<s id="3272146161175325165-2509112046-5" eva="8000320">
    <ar ct="2509112155"/>
    <dp ct="2509112159"/>
</s>


<s id="-8593658168921970782-2509110850-6" eva="8000320">
    <ar ppth="Freilassing|Traunstein|Übersee|Prien am Chiemsee|Bad Endorf" pp="2" ct="2509111122" pt="2509111045" pde="Berchtesgaden Hbf">
        <m id="r24808065" t="f" c="0" ts="2509110703" ts-tts="25-09-11 07:03:16.649"/>
        <m id="r24829643" t="d" c="43" ts="2509110952" ts-tts="25-09-11 09:52:41.417"/>
        <m id="r24829646" t="d" c="43" ts="2509110952" ts-tts="25-09-11 09:52:41.417"/>
        <m id="r24829715" t="f" c="0" ts="2509110953" ts-tts="25-09-11 09:53:12.719"/>
        <m id="r24835781" t="f" c="0" ts="2509111041" ts-tts="25-09-11 10:41:47.887"/>
    </ar>
    <dp ppth="München Ost|München-Pasing|Augsburg Hbf|Donauwörth|Treuchtlingen|Ansbach|Steinach(bei Rothenburg ob der Tauber)|Würzburg Hbf|Fulda|Kassel-Wilhelmshöhe|Göttingen|Hannover Hbf|Celle|Uelzen|Lüneburg|Hamburg-Harburg|Hamburg Hbf|Hamburg Dammtor|Hamburg-Altona" pp="2" ct="2509111124" pt="2509111047">
        <m id="r24808065" t="f" c="0" ts="2509110703" ts-tts="25-09-11 07:03:16.649"/>
        <m id="r24829643" t="d" c="43" ts="2509110952" ts-tts="25-09-11 09:52:41.417"/>
        <m id="r24829646" t="d" c="43" ts="2509110952" ts-tts="25-09-11 09:52:41.417"/>
        <m id="r24829715" t="f" c="0" ts="2509110953" ts-tts="25-09-11 09:53:12.719"/>
        <m id="r24835781" t="f" c="0" ts="2509111041" ts-tts="25-09-11 10:41:47.887"/>
    </dp>
    <tl f="F" t="p" o="80" c="IC" n="2082"/>
</s>


<s id="587913967713533291-2509110937-16" eva="8000320">
    <ar ct="2509111126" l="44">
        <m id="r24824752" t="d" c="21" ts="2509110918" ts-tts="25-09-11 09:18:59.098"/>
    </ar>
</s>


<s id="6067240894965152785-2509111037-13" eva="8000320">
    <ar ct="2509111125" l="RB58">
        <m id="r24839819" t="d" c="48" ts="2509111104" ts-tts="25-09-11 11:04:18.332"/>
    </ar>
</s>


<s id="-2977932392156193232-2509110536-14" eva="8000320">
    <ar ct="2509111117">
        <m id="r24798290" t="d" c="22" ts="2509110518" ts-tts="25-09-11 05:18:58.562"/>
        <m id="r24798292" t="d" c="22" ts="2509110518" ts-tts="25-09-11 05:18:58.562"/>
        <m id="r24798318" t="f" c="0" ts="2509110519" ts-tts="25-09-11 05:19:29.726"/>
        <m id="r24798319" t="f" c="0" ts="2509110519" ts-tts="25-09-11 05:19:29.726"/>
        <m id="r24798320" t="f" c="0" ts="2509110519" ts-tts="25-09-11 05:19:29.726"/>
        <m id="r24798321" t="f" c="0" ts="2509110519" ts-tts="25-09-11 05:19:29.726"/>
        <m id="r24799486" t="f" c="0" ts="2509110537" ts-tts="25-09-11 05:37:19.648"/>
        <m id="r24799487" t="f" c="0" ts="2509110537" ts-tts="25-09-11 05:37:19.648"/>
        <m id="r24799488" t="f" c="0" ts="2509110537" ts-tts="25-09-11 05:37:19.648"/>
        <m id="r24799489" t="f" c="0" ts="2509110537" ts-tts="25-09-11 05:37:19.648"/>
        <m id="r24835194" t="f" c="0" ts="2509111037" ts-tts="25-09-11 10:37:36.582"/>
        <m id="r24835195" t="f" c="0" ts="2509111037" ts-tts="25-09-11 10:37:36.582"/>
    </ar>
    <dp ct="2509111121">
        <m id="r24798290" t="d" c="22" ts="2509110518" ts-tts="25-09-11 05:18:58.562"/>
        <m id="r24798292" t="d" c="22" ts="2509110518" ts-tts="25-09-11 05:18:58.562"/>
        <m id="r24798318" t="f" c="0" ts="2509110519" ts-tts="25-09-11 05:19:29.726"/>
        <m id="r24798319" t="f" c="0" ts="2509110519" ts-tts="25-09-11 05:19:29.726"/>
        <m id="r24798320" t="f" c="0" ts="2509110519" ts-tts="25-09-11 05:19:29.726"/>
        <m id="r24798321" t="f" c="0" ts="2509110519" ts-tts="25-09-11 05:19:29.726"/>
        <m id="r24799486" t="f" c="0" ts="2509110537" ts-tts="25-09-11 05:37:19.648"/>
        <m id="r24799487" t="f" c="0" ts="2509110537" ts-tts="25-09-11 05:37:19.648"/>
        <m id="r24799488" t="f" c="0" ts="2509110537" ts-tts="25-09-11 05:37:19.648"/>
        <m id="r24799489" t="f" c="0" ts="2509110537" ts-tts="25-09-11 05:37:19.648"/>
        <m id="r24835194" t="f" c="0" ts="2509111037" ts-tts="25-09-11 10:37:36.582"/>
        <m id="r24835195" t="f" c="0" ts="2509111037" ts-tts="25-09-11 10:37:36.582"/>
    </dp>
</s>


<s id="42291113023936412-2509111040-1" eva="8000320">
    <dp ct="2509111040" l="RB58"/>
</s>


<s id="7445535174521841037-2509110955-3" eva="8000320">
    <ar ct="2509111036" l="RE5"/>
    <dp ct="2509111038" l="RE5"/>
</s>


<s id="-3214626209625496510-2509111002-7" eva="8000320">
    <ar ct="2509111034" l="RB54">
        <m id="r24796540" t="f" c="1000" ts="2509110453" ts-tts="25-09-11 04:54:13.950"/>
        <m id="r24796609" t="d" c="31" ts="2509110453" ts-tts="25-09-11 04:54:13.950"/>
    </ar>
    <dp ct="2509111038" l="RB54">
        <m id="r24796540" t="f" c="1000" ts="2509110453" ts-tts="25-09-11 04:54:13.950"/>
        <m id="r24796609" t="d" c="31" ts="2509110453" ts-tts="25-09-11 04:54:13.950"/>
    </dp>
</s>


<s id="725406893525714757-2509110941-7" eva="8000320">
    <ar ct="2509111034" l="RB54">
        <m id="r24796538" t="f" c="1000" ts="2509110453" ts-tts="25-09-11 04:54:13.949"/>
        <m id="r24796621" t="d" c="31" ts="2509110454" ts-tts="25-09-11 04:54:13.949"/>
        <m id="r24833283" t="f" c="1000" ts="2509111022" ts-tts="25-09-11 10:22:58.891"/>
        <m id="r24833284" t="d" c="45" ts="2509111022" ts-tts="25-09-11 10:22:58.891"/>
        <m id="r24833285" t="d" c="45" ts="2509111022" ts-tts="25-09-11 10:22:58.891"/>
    </ar>
    <dp ct="2509111036" l="RB54">
        <m id="r24796538" t="f" c="1000" ts="2509110453" ts-tts="25-09-11 04:54:13.949"/>
        <m id="r24796621" t="d" c="31" ts="2509110454" ts-tts="25-09-11 04:54:13.949"/>
        <m id="r24833283" t="f" c="1000" ts="2509111022" ts-tts="25-09-11 10:22:58.891"/>
        <m id="r24833284" t="d" c="45" ts="2509111022" ts-tts="25-09-11 10:22:58.891"/>
        <m id="r24833285" t="d" c="45" ts="2509111022" ts-tts="25-09-11 10:22:58.891"/>
    </dp>
</s>


<s id="6742662918421721387-2509111034-1" eva="8000320">
    <dp ct="2509111035" l="44"/>
</s>


<s id="7951042695241635765-2509110712-7" eva="8000320">
    <ar ct="2509111028">
        <m id="r24785449" t="f" c="1000" ts="2509102312" ts-tts="25-09-10 23:13:01.340"/>
        <m id="r24785458" t="f" c="0" ts="2509102312" ts-tts="25-09-10 23:13:01.340"/>
        <m id="r24785459" t="f" c="0" ts="2509102312" ts-tts="25-09-10 23:13:01.340"/>
    </ar>
    <dp ct="2509111029">
        <m id="r24785449" t="f" c="1000" ts="2509102312" ts-tts="25-09-10 23:13:01.340"/>
        <m id="r24785458" t="f" c="0" ts="2509102312" ts-tts="25-09-10 23:13:01.340"/>
        <m id="r24785459" t="f" c="0" ts="2509102312" ts-tts="25-09-10 23:13:01.340"/>
    </dp>
</s>


<s id="5393359466279466051-2509110905-10" eva="8000320">
    <ar ct="2509111029" l="RE5"/>
    <dp ct="2509111030" l="RE5"/>
</s>


<s id="-7420712075117702882-2509110944-1" eva="8000320">
    <dp ct="2509110948" l="RB58">
        <m id="r24830338" t="d" c="43" ts="2509110958" ts-tts="25-09-11 09:58:41.302"/>
        <m id="r24833494" t="d" c="48" ts="2509111024" ts-tts="25-09-11 10:24:33.089"/>
        <m id="r24833496" t="d" c="48" ts="2509111024" ts-tts="25-09-11 10:24:33.089"/>
        <m id="r24833498" t="d" c="48" ts="2509111024" ts-tts="25-09-11 10:24:33.089"/>
    </dp>
</s>


<s id="-6931307404969666740-2509110937-13" eva="8000320">
    <ar ct="2509111026" l="RB58">
        <m id="r24830670" t="d" c="43" ts="2509111001" ts-tts="25-09-11 10:01:34.469"/>
        <m id="r24830672" t="d" c="43" ts="2509111001" ts-tts="25-09-11 10:01:34.469"/>
    </ar>
</s>


<s id="2439458591958294933-2509110933-9" eva="8000320">
    <ar ct="2509111024" l="44"/>
</s>


<s id="-3916705688291524137-2509110933-3" eva="8000320">
    <ar ct="2509111017">
        <m id="r24833064" t="d" c="43" ts="2509111021" ts-tts="25-09-11 10:21:24.987"/>
        <m id="r24833067" t="d" c="43" ts="2509111021" ts-tts="25-09-11 10:21:24.987"/>
        <m id="r24833070" t="d" c="43" ts="2509111021" ts-tts="25-09-11 10:21:24.987"/>
    </ar>
    <dp ct="2509111018">
        <m id="r24833064" t="d" c="43" ts="2509111021" ts-tts="25-09-11 10:21:24.987"/>
        <m id="r24833067" t="d" c="43" ts="2509111021" ts-tts="25-09-11 10:21:24.987"/>
        <m id="r24833070" t="d" c="43" ts="2509111021" ts-tts="25-09-11 10:21:24.987"/>
    </dp>
</s>


<s id="6414738295846928746-2509101944-21" eva="8000320">
    <ar ppth="Warszawa Wschodnia|Warszawa Centralna|Warszawa Zachodnia|Opoczno Poludnie|Wloszczowa Polnoc|Miechow|Krakow Glowny|Skawina|Oswiecim|Czechowice-Dziedzice|Zebrzydowice|Bohumin|Ostrava hl.n.|Breclav|Wien Hbf|Wien Meidling|St.Pölten Hbf|Linz Hbf|Attnang-Puchheim|Salzburg Hbf" pp="2" ct="2509111013" pt="2509110942" wings="-7091436777592989374-2509101944">
        <m id="r24823000" t="d" c="67" ts="2509110907" ts-tts="25-09-11 09:07:30.454"/>
        <m id="r24823003" t="d" c="67" ts="2509110907" ts-tts="25-09-11 09:07:30.454"/>
        <m id="r24823730" t="f" c="0" ts="2509110910" ts-tts="25-09-11 09:10:54.226"/>
        <m id="r24823731" t="f" c="0" ts="2509110910" ts-tts="25-09-11 09:10:54.226"/>
    </ar>
    <dp ppth="München Ost|München Hbf" pp="2" ct="2509111015" pt="2509110944" hi="1" wings="-7091436777592989374-2509101944">
        <m id="r24823000" t="d" c="67" ts="2509110907" ts-tts="25-09-11 09:07:30.454"/>
        <m id="r24823003" t="d" c="67" ts="2509110907" ts-tts="25-09-11 09:07:30.454"/>
        <m id="r24823730" t="f" c="0" ts="2509110910" ts-tts="25-09-11 09:10:54.226"/>
        <m id="r24823731" t="f" c="0" ts="2509110910" ts-tts="25-09-11 09:10:54.226"/>
    </dp>
    <tl f="F" t="p" o="51" c="EN" n="407"/>
</s>


<s id="-7091436777592989374-2509101944-21" eva="8000320">
    <m id="r2488123" t="h" from="2509080000" to="2512132359" cat="Information" ts="2509080956" ts-tts="25-09-09 23:16:04.917" pr="1"/>
    <ar ppth="Warszawa Wschodnia|Warszawa Centralna|Warszawa Zachodnia|Opoczno Poludnie|Wloszczowa Polnoc|Miechow|Krakow Glowny|Skawina|Oswiecim|Czechowice-Dziedzice|Zebrzydowice|Bohumin|Ostrava hl.n.|Breclav|Wien Hbf|Wien Meidling|St.Pölten Hbf|Linz Hbf|Attnang-Puchheim|Salzburg Hbf" pp="2" ct="2509111013" pt="2509110942">
        <m id="r24822772" t="d" c="67" ts="2509110905" ts-tts="25-09-11 09:05:40.625"/>
        <m id="r24822774" t="d" c="67" ts="2509110905" ts-tts="25-09-11 09:05:40.625"/>
        <m id="r24823725" t="f" c="0" ts="2509110910" ts-tts="25-09-11 09:10:54.226"/>
    </ar>
    <dp ppth="München Ost|München Hbf" pp="2" ct="2509111015" pt="2509110944" hi="1">
        <m id="r24822772" t="d" c="67" ts="2509110905" ts-tts="25-09-11 09:05:40.625"/>
        <m id="r24822774" t="d" c="67" ts="2509110905" ts-tts="25-09-11 09:05:40.625"/>
        <m id="r24823725" t="f" c="0" ts="2509110910" ts-tts="25-09-11 09:10:54.226"/>
    </dp>
    <tl f="F" t="p" o="NZ" c="IC" n="60407"/>
</s>


<s id="6992012378128167215-2509101956-11" eva="8000320">
    <m id="r990660792" t="c" ts="2509110917" ts-tts="25-09-11 09:17:09.626"/>
    <ar ppth="Hamburg-Altona|Hamburg Hbf|Hamburg-Harburg|Hannover Hbf|Göttingen|Kassel-Wilhelmshöhe|Würzburg Hbf|Nürnberg Hbf|Augsburg Hbf|München Hbf" pp="5" ct="2509110955" pt="2509110804">
        <m id="r24768219" t="f" c="0" ts="2509101949" ts-tts="25-09-10 19:50:02.773"/>
        <m id="r24772228" t="d" c="43" ts="2509102027" ts-tts="25-09-10 20:27:04.759"/>
        <m id="r24800875" t="d" c="24" ts="2509110556" ts-tts="25-09-11 05:56:58.673"/>
        <m id="r24800877" t="d" c="24" ts="2509110556" ts-tts="25-09-11 05:56:58.673"/>
        <m id="r24800881" t="d" c="24" ts="2509110556" ts-tts="25-09-11 05:56:58.673"/>
    </ar>
    <dp ppth="Kufstein|Wörgl Hbf|Jenbach|Innsbruck Hbf" pp="5" ct="2509110957" pt="2509110806">
        <m id="r24768219" t="f" c="0" ts="2509101949" ts-tts="25-09-10 19:50:02.773"/>
        <m id="r24772228" t="d" c="43" ts="2509102027" ts-tts="25-09-10 20:27:04.759"/>
        <m id="r24800875" t="d" c="24" ts="2509110556" ts-tts="25-09-11 05:56:58.673"/>
        <m id="r24800877" t="d" c="24" ts="2509110556" ts-tts="25-09-11 05:56:58.673"/>
        <m id="r24800881" t="d" c="24" ts="2509110556" ts-tts="25-09-11 05:56:58.673"/>
    </dp>
    <tl t="p" o="81" c="NJ" n="40491"/>
</s>


<s id="-3823254010841261196-2509101900-11" eva="8000320">
    <m id="r990660791" t="c" ts="2509110917" ts-tts="25-09-11 09:17:09.626"/>
    <ar ppth="Amsterdam Centraal|Amersfoort Centraal|Deventer|Münster(Westf)Hbf|Hamm(Westf)Hbf|Kassel-Wilhelmshöhe|Würzburg Hbf|Nürnberg Hbf|Augsburg Hbf|München Hbf" pp="5" ct="2509110955" pt="2509110804" wings="6992012378128167215-2509101956">
        <m id="r24771296" t="d" c="24" ts="2509102017" ts-tts="25-09-10 20:17:22.313"/>
        <m id="r24771301" t="d" c="24" ts="2509102017" ts-tts="25-09-10 20:17:22.313"/>
        <m id="r24799756" t="f" c="0" ts="2509110541" ts-tts="25-09-11 05:41:27.731"/>
        <m id="r24808519" t="f" c="0" ts="2509110706" ts-tts="25-09-11 07:06:24.447"/>
    </ar>
    <dp ppth="Kufstein|Wörgl Hbf|Jenbach|Innsbruck Hbf" pp="5" ct="2509110957" pt="2509110806" wings="6992012378128167215-2509101956">
        <m id="r24771296" t="d" c="24" ts="2509102017" ts-tts="25-09-10 20:17:22.313"/>
        <m id="r24771301" t="d" c="24" ts="2509102017" ts-tts="25-09-10 20:17:22.313"/>
        <m id="r24799756" t="f" c="0" ts="2509110541" ts-tts="25-09-11 05:41:27.731"/>
        <m id="r24808519" t="f" c="0" ts="2509110706" ts-tts="25-09-11 07:06:24.447"/>
    </dp>
    <tl t="p" o="84" c="NJ" n="421"/>
</s>


<s id="8983673647294408675-2509110842-5" eva="8000320">
    <ar ct="2509110948"/>
    <dp ct="2509110950"/>
</s>


<s id="-5244643378637645953-2509110856-3" eva="8000320">
    <ar ct="2509110933" l="RE5">
        <m id="r24828402" t="d" c="43" ts="2509110944" ts-tts="25-09-11 09:44:20.406"/>
        <m id="r24829175" t="d" c="45" ts="2509110949" ts-tts="25-09-11 09:49:33.834"/>
    </ar>
    <dp ct="2509110938" l="RE5">
        <m id="r24828402" t="d" c="43" ts="2509110944" ts-tts="25-09-11 09:44:20.406"/>
        <m id="r24829175" t="d" c="45" ts="2509110949" ts-tts="25-09-11 09:49:33.834"/>
    </dp>
</s>


<s id="7396583960461598380-2509111705-10" eva="8000320">
    <ar ct="2509111825" l="RE5"/>
    <dp ct="2509111829" l="RE5"/>
</s>


<s id="5677798296789313454-2509111407-10" eva="8000320">
    <ar ct="2509111525" l="RE5"/>
    <dp ct="2509111529" l="RE5"/>
</s>


<s id="5148087305384451929-2509111605-10" eva="8000320">
    <ar ct="2509111725" l="RE5"/>
    <dp ct="2509111729" l="RE5"/>
</s>


<s id="4256388425074954618-2509111905-10" eva="8000320">
    <ar ct="2509112025" l="RE5"/>
    <dp ct="2509112032" l="RE5"/>
</s>


<s id="2931906224447066494-2509112252-11" eva="8000320">
    <ar ct="2509120009" l="RE5"/>
    <dp ct="2509120012" l="RE5"/>
</s>


<s id="-7173871107655325076-2509111808-10" eva="8000320">
    <ar ct="2509111925" l="RE5"/>
    <dp ct="2509111929" l="RE5"/>
</s>


<s id="-7043471499230465318-2509112208-10" eva="8000320">
    <ar ct="2509112326" l="RE5"/>
    <dp ct="2509112332" l="RE5"/>
</s>


<s id="-5799573306990257518-2509111505-10" eva="8000320">
    <ar ct="2509111625" l="RE5"/>
    <dp ct="2509111629" l="RE5"/>
</s>


<s id="-5652708052565312131-2509112108-10" eva="8000320">
    <ar ct="2509112228" l="RE5"/>
    <dp ct="2509112233" l="RE5"/>
</s>


<s id="-3341117925818028704-2509112005-10" eva="8000320">
    <ar ct="2509112125" l="RE5"/>
    <dp ct="2509112132" l="RE5"/>
</s>


<s id="2556562000023491447-2509110608-10" eva="8000320">
    <ar cp="2" ct="2509110942">
        <m id="r24785263" t="f" c="1000" ts="2509102309" ts-tts="25-09-10 23:09:54.913"/>
        <m id="r24785410" t="f" c="0" ts="2509102312" ts-tts="25-09-10 23:12:30.152"/>
        <m id="r24785411" t="f" c="0" ts="2509102312" ts-tts="25-09-10 23:12:30.152"/>
    </ar>
    <dp cp="2" ct="2509110944">
        <m id="r24785263" t="f" c="1000" ts="2509102309" ts-tts="25-09-10 23:09:54.913"/>
        <m id="r24785410" t="f" c="0" ts="2509102312" ts-tts="25-09-10 23:12:30.152"/>
        <m id="r24785411" t="f" c="0" ts="2509102312" ts-tts="25-09-10 23:12:30.152"/>
    </dp>
</s>


<s id="8876872294131275319-2509110902-7" eva="8000320">
    <ar ct="2509110937" l="RB54">
        <m id="r24796537" t="f" c="1000" ts="2509110453" ts-tts="25-09-11 04:54:13.950"/>
        <m id="r24796625" t="d" c="31" ts="2509110454" ts-tts="25-09-11 04:54:13.950"/>
    </ar>
    <dp ct="2509110942" l="RB54">
        <m id="r24796537" t="f" c="1000" ts="2509110453" ts-tts="25-09-11 04:54:13.950"/>
        <m id="r24796625" t="d" c="31" ts="2509110454" ts-tts="25-09-11 04:54:13.950"/>
    </dp>
</s>


<s id="5058114512956515493-2509110835-13" eva="8000320">
    <ar ct="2509110939" l="RB58"/>
</s>


<s id="8447355569633060280-2509110934-1" eva="8000320">
    <dp ct="2509110934" l="44"/>
</s>


<s id="-7546488962176627799-2509110805-10" eva="8000320">
    <ar ct="2509110934" l="RE5">
        <m id="r24823935" t="d" c="38" ts="2509110912" ts-tts="25-09-11 09:12:28.157"/>
    </ar>
    <dp ct="2509110934" l="RE5">
        <m id="r24823935" t="d" c="38" ts="2509110912" ts-tts="25-09-11 09:12:28.157"/>
    </dp>
</s>


<s id="3023402330088844269-2509110843-7" eva="8000320">
    <ar ct="2509110928" l="RB54">
        <m id="r24796527" t="f" c="1000" ts="2509110453" ts-tts="25-09-11 04:54:13.949"/>
        <m id="r24796601" t="d" c="31" ts="2509110453" ts-tts="25-09-11 04:54:13.949"/>
        <m id="r24796602" t="d" c="31" ts="2509110453" ts-tts="25-09-11 04:54:13.949"/>
    </ar>
    <dp ct="2509110932" l="RB54">
        <m id="r24796527" t="f" c="1000" ts="2509110453" ts-tts="25-09-11 04:54:13.949"/>
        <m id="r24796601" t="d" c="31" ts="2509110453" ts-tts="25-09-11 04:54:13.949"/>
        <m id="r24796602" t="d" c="31" ts="2509110453" ts-tts="25-09-11 04:54:13.949"/>
    </dp>
</s>


<s id="-4269321884350482154-2509110737-16" eva="8000320">
    <ar cp="1a" ct="2509110925" l="44"/>
</s>


<s id="6192241728504658110-2509110749-3" eva="8000320">
    <ar ct="2509110829">
        <m id="r24785415" t="f" c="1000" ts="2509102312" ts-tts="25-09-10 23:12:30.152"/>
        <m id="r24785481" t="f" c="0" ts="2509102313" ts-tts="25-09-10 23:13:16.918"/>
        <m id="r24785482" t="f" c="0" ts="2509102313" ts-tts="25-09-10 23:13:16.918"/>
    </ar>
    <dp ct="2509110831">
        <m id="r24785415" t="f" c="1000" ts="2509102312" ts-tts="25-09-10 23:12:30.152"/>
        <m id="r24785481" t="f" c="0" ts="2509102313" ts-tts="25-09-10 23:13:16.918"/>
        <m id="r24785482" t="f" c="0" ts="2509102313" ts-tts="25-09-10 23:13:16.918"/>
        <m id="r24824532" t="f" c="0" ts="2509110917" ts-tts="25-09-11 09:17:09.757"/>
        <m id="r24824533" t="f" c="0" ts="2509110917" ts-tts="25-09-11 09:17:09.757"/>
    </dp>
</s>


<s id="588518337148996735-2509110738-20" eva="8000320">
    <ar cp="7" ct="2509110902" l="RB58"/>
</s>


<s id="-7786451860906192256-2509110837-1" eva="8000320">
    <dp ct="2509110838" l="RB58"/>
</s>


<s id="7908960142862658587-2509110802-7" eva="8000320">
    <ar ct="2509110832" l="RB54">
        <m id="r24796529" t="f" c="1000" ts="2509110453" ts-tts="25-09-11 04:54:13.950"/>
        <m id="r24796629" t="d" c="31" ts="2509110454" ts-tts="25-09-11 04:54:13.950"/>
        <m id="r24796630" t="d" c="31" ts="2509110454" ts-tts="25-09-11 04:54:13.950"/>
    </ar>
    <dp ct="2509110836" l="RB54">
        <m id="r24796529" t="f" c="1000" ts="2509110453" ts-tts="25-09-11 04:54:13.950"/>
        <m id="r24796629" t="d" c="31" ts="2509110454" ts-tts="25-09-11 04:54:13.950"/>
        <m id="r24796630" t="d" c="31" ts="2509110454" ts-tts="25-09-11 04:54:13.950"/>
    </dp>
</s>


<s id="274168274112904353-2509110756-3" eva="8000320">
    <ar ct="2509110834" l="RE5"/>
    <dp ct="2509110835" l="RE5"/>
</s>


<s id="8076250263419784645-2509110834-1" eva="8000320">
    <dp ct="2509110834" l="44"/>
</s>


<s id="458601506753089479-2509110655-3" eva="8000320">
    <ar ct="2509110742" l="RE5">
        <m id="r24818658" t="f" c="1000" ts="2509110832" ts-tts="25-09-11 08:32:48.749"/>
        <m id="r24818662" t="d" c="42" ts="2509110832" ts-tts="25-09-11 08:32:48.749"/>
        <m id="r24818663" t="d" c="42" ts="2509110832" ts-tts="25-09-11 08:32:48.749"/>
    </ar>
    <dp ct="2509110743" l="RE5">
        <m id="r24818658" t="f" c="1000" ts="2509110832" ts-tts="25-09-11 08:32:48.749"/>
        <m id="r24818662" t="d" c="42" ts="2509110832" ts-tts="25-09-11 08:32:48.749"/>
        <m id="r24818663" t="d" c="42" ts="2509110832" ts-tts="25-09-11 08:32:48.749"/>
    </dp>
</s>


<s id="-9893488643141506-2509110738-7" eva="8000320">
    <ar ct="2509110827" l="RB54">
        <m id="r24796521" t="f" c="1000" ts="2509110453" ts-tts="25-09-11 04:54:13.948"/>
        <m id="r24796603" t="d" c="31" ts="2509110453" ts-tts="25-09-11 04:54:13.948"/>
        <m id="r24796606" t="d" c="31" ts="2509110453" ts-tts="25-09-11 04:54:13.948"/>
    </ar>
    <dp ct="2509110832" l="RB54">
        <m id="r24796521" t="f" c="1000" ts="2509110453" ts-tts="25-09-11 04:54:13.948"/>
        <m id="r24796603" t="d" c="31" ts="2509110453" ts-tts="25-09-11 04:54:13.948"/>
        <m id="r24796606" t="d" c="31" ts="2509110453" ts-tts="25-09-11 04:54:13.949"/>
    </dp>
</s>


<s id="-9104683804530937782-2509110722-9" eva="8000320">
    <ar ct="2509110825" l="RE5"/>
    <dp ct="2509110829" l="RE5"/>
</s>


<s id="1461716935599267385-2509101810-9" eva="8000320">
    <ar ct="2509110830">
        <m id="r24799620" t="d" c="24" ts="2509110539" ts-tts="25-09-11 05:39:54.789"/>
        <m id="r24799622" t="d" c="24" ts="2509110539" ts-tts="25-09-11 05:39:54.789"/>
    </ar>
    <dp ct="2509110838">
        <m id="r24799620" t="d" c="24" ts="2509110539" ts-tts="25-09-11 05:39:54.789"/>
        <m id="r24799622" t="d" c="24" ts="2509110539" ts-tts="25-09-11 05:39:54.789"/>
    </dp>
</s>


<s id="-2250584550180352138-2509102054-13" eva="8000320">
    <ar ct="2509110831">
        <m id="r24799616" t="d" c="24" ts="2509110539" ts-tts="25-09-11 05:39:54.789"/>
        <m id="r24799618" t="d" c="24" ts="2509110539" ts-tts="25-09-11 05:39:54.789"/>
    </ar>
    <dp ct="2509110838">
        <m id="r24799616" t="d" c="24" ts="2509110539" ts-tts="25-09-11 05:39:54.789"/>
        <m id="r24799618" t="d" c="24" ts="2509110539" ts-tts="25-09-11 05:39:54.789"/>
    </dp>
</s>


<s id="5486444751985215945-2509110729-10" eva="8000320">
    <ar ct="2509110827" l="44"/>
</s>


<s id="-3987775852530243673-2509110735-11" eva="8000320">
    <ar ct="2509110825" l="RB58"/>
</s>


<s id="8395670745039412438-2509110732-3" eva="8000320">
    <ar ct="2509110814"/>
    <dp ct="2509110816"/>
</s>


<s id="3284493521676504263-2509110708-6" eva="8000320">
    <m id="r2488123" t="h" from="2509080000" to="2512132359" cat="Information" ts="2509080956" ts-tts="25-09-10 23:16:04.767" pr="1"/>
    <ar ct="2509110815"/>
    <dp ct="2509110819"/>
</s>


<s id="1344312182465599860-2509110730-7" eva="8000320">
    <ar ct="2509110802" l="RB54">
        <m id="r24796526" t="f" c="1000" ts="2509110453" ts-tts="25-09-11 04:54:13.950"/>
        <m id="r24796619" t="d" c="31" ts="2509110454" ts-tts="25-09-11 04:54:13.950"/>
        <m id="r24796620" t="d" c="31" ts="2509110454" ts-tts="25-09-11 04:54:13.950"/>
    </ar>
    <dp ct="2509110808" l="RB54">
        <m id="r24796526" t="f" c="1000" ts="2509110453" ts-tts="25-09-11 04:54:13.950"/>
        <m id="r24796619" t="d" c="31" ts="2509110454" ts-tts="25-09-11 04:54:13.950"/>
        <m id="r24796620" t="d" c="31" ts="2509110454" ts-tts="25-09-11 04:54:13.950"/>
    </dp>
</s>


<s id="-4786939453638068085-2509110646-10" eva="8000320">
    <ar ct="2509110803" l="RE5"/>
    <dp ct="2509110808" l="RE5"/>
</s>


<s id="-3232591964701209830-2509110803-1" eva="8000320">
    <dp ct="2509110803" l="RB58"/>
</s>


<s id="-6482643182545866913-2509110638-21" eva="8000320">
    <ar ct="2509110801" l="RB58"/>
</s>


<s id="5066262228801266180-2509110659-7" eva="8000320">
    <ar cp="1" ct="2509110751" l="RB54">
        <m id="r24811702" t="d" c="43" ts="2509110735" ts-tts="25-09-11 07:36:10.037"/>
        <m id="r24814549" t="d" c="43" ts="2509110757" ts-tts="25-09-11 07:57:50.840"/>
    </ar>
</s>


<s id="7801371309014269710-2509110722-2" eva="8000320">
    <ar ct="2509110758">
        <m id="r24814231" t="f" c="0" ts="2509110755" ts-tts="25-09-11 07:55:29.319"/>
    </ar>
    <dp ct="2509110803">
        <m id="r24814231" t="f" c="0" ts="2509110755" ts-tts="25-09-11 07:55:29.319"/>
    </dp>
</s>


<s id="2445748007328325452-2509101912-4" eva="8000320">
    <ar ppth="Paris Est|Mannheim Hbf|München Ost" cp="5" pp="4" ct="2509110751" pt="2509110716" wings="-4775919377312079274-2509101906">
        <m id="r24626593" t="d" c="67" ts="2509092105" ts-tts="25-09-09 21:05:52.494"/>
        <m id="r24626595" t="d" c="67" ts="2509092105" ts-tts="25-09-09 21:05:52.494"/>
        <m id="r24626597" t="d" c="67" ts="2509092105" ts-tts="25-09-09 21:05:52.494"/>
        <m id="r24782269" t="q" c="98" ts="2509102217" ts-tts="25-09-10 22:17:48.836"/>
        <m id="r24782271" t="q" c="98" ts="2509102217" ts-tts="25-09-10 22:17:48.836"/>
        <m id="r24790078" t="f" c="0" ts="2509110103" ts-tts="25-09-11 01:03:29.544"/>
    </ar>
    <dp ppth="Freilassing|Salzburg Hbf|Linz Hbf|St.Pölten Hbf|Wien Meidling|Wien Hbf" cp="5" pp="4" ct="2509110752" pt="2509110718" wings="-4775919377312079274-2509101906">
        <m id="r24626593" t="d" c="67" ts="2509092105" ts-tts="25-09-09 21:05:52.494"/>
        <m id="r24626595" t="d" c="67" ts="2509092105" ts-tts="25-09-09 21:05:52.494"/>
        <m id="r24626597" t="d" c="67" ts="2509092105" ts-tts="25-09-09 21:05:52.494"/>
        <m id="r24782269" t="q" c="98" ts="2509102217" ts-tts="25-09-10 22:17:48.836"/>
        <m id="r24782271" t="q" c="98" ts="2509102217" ts-tts="25-09-10 22:17:48.836"/>
        <m id="r24790078" t="f" c="0" ts="2509110103" ts-tts="25-09-11 01:03:29.544"/>
    </dp>
    <tl t="p" o="81" c="NJ" n="469"/>
</s>


<s id="-4775919377312079274-2509101906-11" eva="8000320">
    <m id="r2488098" t="h" from="2509080000" to="2512132359" cat="Information" ts="2509080945" ts-tts="25-09-09 23:16:04.907" pr="1"/>
    <ar ppth="Bruxelles Midi|Bruxelles-Nord|Liège-Guillemins|Aachen Hbf|Köln Hbf|Bonn-Beuel|Koblenz Hbf|Mainz Hbf|Mannheim Hbf|München Ost" cp="5" pp="4" ct="2509110751" pt="2509110716">
        <m id="r24782331" t="q" c="98" ts="2509102218" ts-tts="25-09-10 22:18:35.711"/>
        <m id="r24782335" t="q" c="98" ts="2509102218" ts-tts="25-09-10 22:18:35.711"/>
        <m id="r24787788" t="d" c="31" ts="2509110012" ts-tts="25-09-11 00:13:03.613"/>
        <m id="r24787792" t="d" c="31" ts="2509110012" ts-tts="25-09-11 00:13:03.613"/>
        <m id="r24790077" t="f" c="0" ts="2509110103" ts-tts="25-09-11 01:03:29.544"/>
    </ar>
    <dp ppth="Freilassing|Salzburg Hbf|Linz Hbf|St.Pölten Hbf|Wien Meidling|Wien Hbf" cp="5" pp="4" ct="2509110752" pt="2509110718">
        <m id="r24782331" t="q" c="98" ts="2509102218" ts-tts="25-09-10 22:18:35.711"/>
        <m id="r24782335" t="q" c="98" ts="2509102218" ts-tts="25-09-10 22:18:35.711"/>
        <m id="r24787788" t="d" c="31" ts="2509110012" ts-tts="25-09-11 00:13:03.613"/>
        <m id="r24787792" t="d" c="31" ts="2509110012" ts-tts="25-09-11 00:13:03.613"/>
        <m id="r24790077" t="f" c="0" ts="2509110103" ts-tts="25-09-11 01:03:29.544"/>
    </dp>
    <tl t="p" o="81" c="NJ" n="40425"/>
</s>


<s id="291083137901228988-2509110642-5" eva="8000320">
    <ar ct="2509110748"/>
    <dp ct="2509110751"/>
</s>


<s id="-5371591381866790248-2509110750-1" eva="8000320">
    <dp ct="2509110750" l="44"/>
</s>


<s id="3565571157491908156-2509110735-1" eva="8000320">
    <dp ct="2509110735" l="RB58"/>
</s>


<s id="3099880514924681889-2509110702-7" eva="8000320">
    <ar ct="2509110729" l="RB54">
        <m id="r24796528" t="f" c="1000" ts="2509110453" ts-tts="25-09-11 04:54:13.950"/>
        <m id="r24796614" t="d" c="31" ts="2509110453" ts-tts="25-09-11 04:54:13.950"/>
        <m id="r24796615" t="d" c="31" ts="2509110453" ts-tts="25-09-11 04:54:13.950"/>
    </ar>
    <dp ct="2509110733" l="RB54">
        <m id="r24796528" t="f" c="1000" ts="2509110453" ts-tts="25-09-11 04:54:13.950"/>
        <m id="r24796614" t="d" c="31" ts="2509110453" ts-tts="25-09-11 04:54:13.950"/>
        <m id="r24796615" t="d" c="31" ts="2509110453" ts-tts="25-09-11 04:54:13.950"/>
    </dp>
</s>


<s id="-5185317119813626433-2509110641-7" eva="8000320">
    <ar ct="2509110727" l="RB54">
        <m id="r24796515" t="f" c="1000" ts="2509110453" ts-tts="25-09-11 04:54:13.948"/>
        <m id="r24796637" t="d" c="31" ts="2509110454" ts-tts="25-09-11 04:54:13.948"/>
        <m id="r24796640" t="d" c="31" ts="2509110454" ts-tts="25-09-11 04:54:13.948"/>
    </ar>
    <dp ct="2509110732" l="RB54">
        <m id="r24796515" t="f" c="1000" ts="2509110453" ts-tts="25-09-11 04:54:13.948"/>
        <m id="r24796637" t="d" c="31" ts="2509110454" ts-tts="25-09-11 04:54:13.948"/>
        <m id="r24796640" t="d" c="31" ts="2509110454" ts-tts="25-09-11 04:54:13.948"/>
    </dp>
</s>


<s id="2700651968204666558-2509110605-10" eva="8000320">
    <ar ct="2509110726" l="RE5"/>
    <dp ct="2509110729" l="RE5"/>
</s>


<s id="5413612924673476662-2509110635-13" eva="8000320">
    <ar ct="2509110725" l="RB58"/>
</s>


<s id="-7451862214851920283-2509110549-11" eva="8000320">
    <ar ct="2509110719" l="44">
        <m id="r24798437" t="d" c="44" ts="2509110521" ts-tts="25-09-11 05:21:34.167"/>
        <m id="r24798439" t="d" c="44" ts="2509110521" ts-tts="25-09-11 05:21:34.167"/>
        <m id="r24800755" t="f" c="0" ts="2509110555" ts-tts="25-09-11 05:55:56.709"/>
        <m id="r24800756" t="f" c="0" ts="2509110555" ts-tts="25-09-11 05:55:56.709"/>
        <m id="r24803103" t="f" c="0" ts="2509110619" ts-tts="25-09-11 06:20:04.450"/>
    </ar>
</s>


<s id="3286237709636034889-2509112300-7" eva="8000320">
    <ar ct="2509112326" l="RB54">
        <m id="r24796583" t="f" c="1000" ts="2509110453" ts-tts="25-09-11 04:54:13.950"/>
        <m id="r24796647" t="d" c="31" ts="2509110454" ts-tts="25-09-11 04:54:13.950"/>
    </ar>
</s>


<s id="9183508140555196637-2509112335-1" eva="8000320">
    <dp ct="2509112335" l="RB54">
        <m id="r24796593" t="f" c="1000" ts="2509110453" ts-tts="25-09-11 04:54:13.948"/>
        <m id="r24796677" t="d" c="31" ts="2509110454" ts-tts="25-09-11 04:54:13.948"/>
        <m id="r24796679" t="d" c="31" ts="2509110454" ts-tts="25-09-11 04:54:13.948"/>
        <m id="r24796681" t="d" c="31" ts="2509110454" ts-tts="25-09-11 04:54:13.948"/>
    </dp>
</s>


<s id="-1231994002280017756-2509112333-1" eva="8000320">
    <dp ct="2509112333" l="RB58"/>
</s>


<s id="-6748349582798644325-2509112344-13" eva="8000320">
    <ar ct="2509120030" l="RB58"/>
</s>


<s id="-4559014619925635287-2509110607-9" eva="8000320">
    <ar ct="2509110710" l="RE5"/>
    <dp ct="2509110712" l="RE5"/>
</s>


<s id="5279283621341660290-2509110621-3" eva="8000320">
    <ar ct="2509110700">
        <m id="r24804620" t="q" c="98" ts="2509110633" ts-tts="25-09-11 06:34:06.230"/>
        <m id="r24804622" t="q" c="98" ts="2509110633" ts-tts="25-09-11 06:34:06.230"/>
    </ar>
    <dp ct="2509110703">
        <m id="r24804620" t="q" c="98" ts="2509110633" ts-tts="25-09-11 06:34:06.230"/>
        <m id="r24804622" t="q" c="98" ts="2509110633" ts-tts="25-09-11 06:34:06.230"/>
    </dp>
</s>


<s id="2152476824149645318-2509110626-7" eva="8000320">
    <ar cp="2" ct="2509110659" l="RB54">
        <m id="r24796520" t="f" c="1000" ts="2509110453" ts-tts="25-09-11 04:54:13.950"/>
        <m id="r24796600" t="d" c="31" ts="2509110453" ts-tts="25-09-11 04:54:13.950"/>
    </ar>
    <dp cp="2" ct="2509110700" l="RB54">
        <m id="r24796520" t="f" c="1000" ts="2509110453" ts-tts="25-09-11 04:54:13.950"/>
        <m id="r24796600" t="d" c="31" ts="2509110453" ts-tts="25-09-11 04:54:13.950"/>
    </dp>
</s>


<s id="-2116457302243711079-2509110658-1" eva="8000320">
    <dp ct="2509110700" l="RB54">
        <m id="r24796507" t="f" c="1000" ts="2509110453" ts-tts="25-09-11 04:54:13.948"/>
        <m id="r24796611" t="d" c="31" ts="2509110453" ts-tts="25-09-11 04:54:13.948"/>
        <m id="r24796612" t="d" c="31" ts="2509110453" ts-tts="25-09-11 04:54:13.948"/>
    </dp>
</s>


<s id="3906300348358769264-2509110659-1" eva="8000320">
    <dp cp="6" ct="2509110659" l="RB58"/>
</s>


<s id="84528615131372682-2509110600-7" eva="8000320">
    <ar ct="2509110642" l="RE5"/>
    <dp ct="2509110645" l="RE5"/>
</s>


<s id="6801729035174711983-2509110552-7" eva="8000320">
    <ar ct="2509110638" l="RE5"/>
    <dp ct="2509110639" l="RE5"/>
</s>


<s id="6472173549963532985-2509110637-1" eva="8000320">
    <dp ct="2509110637" l="RB58"/>
</s>


<s id="2512296643368996801-2509110600-7" eva="8000320">
    <ar ct="2509110627" l="RB54">
        <m id="r24796519" t="f" c="1000" ts="2509110453" ts-tts="25-09-11 04:54:13.949"/>
        <m id="r24796610" t="d" c="31" ts="2509110453" ts-tts="25-09-11 04:54:13.949"/>
        <m id="r24796613" t="d" c="31" ts="2509110453" ts-tts="25-09-11 04:54:13.949"/>
    </ar>
    <dp ct="2509110633" l="RB54">
        <m id="r24796519" t="f" c="1000" ts="2509110453" ts-tts="25-09-11 04:54:13.949"/>
        <m id="r24796610" t="d" c="31" ts="2509110453" ts-tts="25-09-11 04:54:13.949"/>
        <m id="r24796613" t="d" c="31" ts="2509110453" ts-tts="25-09-11 04:54:13.949"/>
    </dp>
</s>


<s id="-3558209705404887939-2509110505-10" eva="8000320">
    <ar ct="2509110625" l="RE5"/>
    <dp ct="2509110629" l="RE5"/>
</s>


<s id="-8691765711665412790-2509110617-1" eva="8000320">
    <dp ct="2509110617" l="44">
        <m id="r24798774" t="f" c="0" ts="2509110527" ts-tts="25-09-11 05:27:30.560"/>
    </dp>
</s>


<s id="-1228993334264947830-2509112200-7" eva="8000320">
    <ar ct="2509112226" l="RB54">
        <m id="r24796585" t="f" c="1000" ts="2509110453" ts-tts="25-09-11 04:54:13.950"/>
        <m id="r24796650" t="d" c="31" ts="2509110454" ts-tts="25-09-11 04:54:13.950"/>
        <m id="r24796653" t="d" c="31" ts="2509110454" ts-tts="25-09-11 04:54:13.950"/>
        <m id="r24796655" t="d" c="31" ts="2509110454" ts-tts="25-09-11 04:54:13.950"/>
    </ar>
</s>


<s id="6928715414301850711-2509112235-1" eva="8000320">
    <dp ct="2509112235" l="RB54">
        <m id="r24796591" t="f" c="1000" ts="2509110453" ts-tts="25-09-11 04:54:13.948"/>
        <m id="r24796675" t="d" c="31" ts="2509110454" ts-tts="25-09-11 04:54:13.948"/>
        <m id="r24796676" t="d" c="31" ts="2509110454" ts-tts="25-09-11 04:54:13.948"/>
        <m id="r24796678" t="d" c="31" ts="2509110454" ts-tts="25-09-11 04:54:13.948"/>
    </dp>
</s>


<s id="-6479525194224213497-2509112252-6" eva="8000320">
    <ar ct="2509112327" l="RE5"/>
    <dp ct="2509112335" l="RE5"/>
</s>


<s id="7471611462372991374-2509112237-13" eva="8000320">
    <ar ct="2509112323" l="RB58"/>
</s>


<s id="-2125387422365465848-2509112240-1" eva="8000320">
    <dp ct="2509112240" l="RB58"/>
</s>


<s id="1728464576163601172-2509110601-1" eva="8000320">
    <dp ct="2509110601" l="RB58"/>
</s>


<s id="1564342040995704201-2509110734-1" eva="8000320">
    <m id="r2489651" t="h" from="2509110700" to="2509110830" cat="Störung" ts="2509110539" ts-tts="25-09-11 05:39:39.212" pr="1"/>
    <dp cpth="" cs="c" clt="2509110519" l="44">
        <m id="r24798295" t="f" c="1000" ts="2509110519" ts-tts="25-09-11 05:19:14.019"/>
        <m id="r24798298" t="f" c="0" ts="2509110519" ts-tts="25-09-11 05:19:14.019"/>
    </dp>
</s>


<s id="-852363552926966188-2509110618-11" eva="8000320">
    <m id="r2489650" t="h" from="2509110600" to="2509110730" cat="Störung" ts="2509110537" ts-tts="25-09-11 05:37:19.491" pr="1"/>
    <ar cpth="" cs="c" clt="2509110517" l="44">
        <m id="r24798219" t="f" c="1000" ts="2509110517" ts-tts="25-09-11 05:18:12.057"/>
        <m id="r24798221" t="d" c="54" ts="2509110517" ts-tts="25-09-11 05:18:12.057"/>
        <m id="r24798223" t="d" c="54" ts="2509110517" ts-tts="25-09-11 05:18:12.057"/>
        <m id="r24798225" t="d" c="54" ts="2509110517" ts-tts="25-09-11 05:18:12.057"/>
    </ar>
</s>


<s id="8258495970941561047-2509102105-11" eva="8000320">
    <m id="r2488123" t="h" from="2509080000" to="2512132359" cat="Information" ts="2509080956" ts-tts="25-09-09 23:16:04.917" pr="1"/>
    <ar ct="2509110518"/>
    <dp ct="2509110520"/>
</s>


<s id="6406586649286876666-2509101938-17" eva="8000320">
    <ar ct="2509110518"/>
    <dp ct="2509110520"/>
</s>


<s id="-2509751023840669752-2509102055-11" eva="8000320">
    <ar ct="2509110518"/>
    <dp ct="2509110520"/>
</s>


<s id="-3391534905880055353-2509112100-7" eva="8000320">
    <ar ct="2509112126" l="RB54">
        <m id="r24796584" t="f" c="1000" ts="2509110453" ts-tts="25-09-11 04:54:13.950"/>
        <m id="r24796672" t="d" c="31" ts="2509110454" ts-tts="25-09-11 04:54:13.950"/>
        <m id="r24796673" t="d" c="31" ts="2509110454" ts-tts="25-09-11 04:54:13.950"/>
        <m id="r24796674" t="d" c="31" ts="2509110454" ts-tts="25-09-11 04:54:13.950"/>
    </ar>
</s>


<s id="8258495970941561047-2509112105-11" eva="8000320">
    <m id="r2488123" t="h" from="2509080000" to="2512132359" cat="Information" ts="2509080956" ts-tts="25-09-10 23:16:04.767" pr="1"/>
</s>


<s id="-3059565084633537213-2509112143-7" eva="8000320">
    <ar ct="2509112227" l="RE5"/>
    <dp ct="2509112232" l="RE5"/>
</s>


<s id="8433647612880255595-2509112140-1" eva="8000320">
    <dp ct="2509112140" l="RB58"/>
</s>


<s id="1127135327253611444-2509112137-13" eva="8000320">
    <ar ct="2509112223" l="RB58"/>
</s>


<s id="8917793373340163930-2509111525-3" eva="8000320">
    <ar ct="2509111603" l="RE5"/>
    <dp ct="2509111615" l="RE5"/>
</s>


<s id="5415590645821435174-2509111955-3" eva="8000320">
    <ar ct="2509112032" l="RE5"/>
    <dp ct="2509112035" l="RE5"/>
</s>


<s id="5405929532564193161-2509111722-3" eva="8000320">
    <ar ct="2509111803" l="RE5"/>
    <dp ct="2509111815" l="RE5"/>
</s>


<s id="2984989242016249310-2509111756-3" eva="8000320">
    <ar ct="2509111832" l="RE5"/>
    <dp ct="2509111835" l="RE5"/>
</s>


<s id="2832026240203944514-2509111855-3" eva="8000320">
    <ar ct="2509111933" l="RE5"/>
    <dp ct="2509111935" l="RE5"/>
</s>


<s id="-61161759783622032-2509111555-3" eva="8000320">
    <ar ct="2509111632" l="RE5"/>
    <dp ct="2509111635" l="RE5"/>
</s>


<s id="-5313657216670008844-2509111636-3" eva="8000320">
    <ar ct="2509111711" l="RE5"/>
    <dp ct="2509111714" l="RE5"/>
</s>


<s id="-4231047399366536253-2509111455-3" eva="8000320">
    <ar ct="2509111532" l="RE5"/>
    <dp ct="2509111535" l="RE5"/>
</s>


<s id="-257941477637039660-2509111655-3" eva="8000320">
    <ar ct="2509111732" l="RE5"/>
    <dp ct="2509111735" l="RE5"/>
</s>


<s id="-1793366256904633318-2509112054-3" eva="8000320">
    <ar ct="2509112132" l="RE5"/>
    <dp ct="2509112135" l="RE5"/>
</s>


<s id="8830939802424709464-2509112040-1" eva="8000320">
    <dp ct="2509112040" l="RB58"/>
</s>


<s id="6932072886947352487-2509111437-13" eva="8000320">
    <ar ct="2509111525" l="RB58"/>
</s>


<s id="6552454503974965104-2509111902-1" eva="8000320">
    <dp ct="2509111902" l="RB58"/>
</s>


<s id="3992986466606613663-2509111737-1" eva="8000320">
    <dp ct="2509111737" l="RB58"/>
</s>


<s id="2819344633605492698-2509111537-1" eva="8000320">
    <dp ct="2509111537" l="RB58"/>
</s>


<s id="2816933140469064937-2509111838-20" eva="8000320">
    <ar ct="2509111951" l="RB58"/>
</s>


<s id="2738992994705894098-2509111438-20" eva="8000320">
    <ar ct="2509111551" l="RB58"/>
</s>


<s id="2727726753072538916-2509111535-13" eva="8000320">
    <ar ct="2509111625" l="RB58"/>
</s>


<s id="2304560780912441164-2509111735-13" eva="8000320">
    <ar ct="2509111825" l="RB58"/>
</s>


<s id="2151121283920601532-2509111702-1" eva="8000320">
    <dp ct="2509111702" l="RB58"/>
</s>


<s id="2003969630160897681-2509111738-20" eva="8000320">
    <ar ct="2509111851" l="RB58"/>
</s>


<s id="1364422035544943204-2509111637-1" eva="8000320">
    <dp ct="2509111637" l="RB58"/>
</s>


<s id="-8764110682832311089-2509111802-1" eva="8000320">
    <dp ct="2509111802" l="RB58"/>
</s>


<s id="-8159026682758054821-2509111937-1" eva="8000320">
    <dp ct="2509111937" l="RB58"/>
</s>


<s id="-7631117004556906559-2509111338-20" eva="8000320">
    <ar ct="2509111451" l="RB58"/>
</s>


<s id="-4871586568835123145-2509111602-1" eva="8000320">
    <dp ct="2509111602" l="RB58"/>
</s>


<s id="-4426463060164847352-2509111502-1" eva="8000320">
    <dp ct="2509111502" l="RB58"/>
</s>


<s id="-328234189904227206-2509111935-13" eva="8000320">
    <ar ct="2509112023" l="RB58"/>
</s>


<s id="-3133519533882879889-2509111835-13" eva="8000320">
    <ar ct="2509111925" l="RB58"/>
</s>


<s id="-2384779135040445299-2509111638-20" eva="8000320">
    <ar ct="2509111751" l="RB58"/>
</s>


<s id="-1852853268478535427-2509111837-1" eva="8000320">
    <dp ct="2509111837" l="RB58"/>
</s>


<s id="-1622650275379069863-2509111538-20" eva="8000320">
    <ar ct="2509111654" l="RB58"/>
</s>


<s id="-1211240558580121676-2509112037-13" eva="8000320">
    <ar ct="2509112126" l="RB58"/>
</s>


<s id="-1129282866591070162-2509111635-13" eva="8000320">
    <ar ct="2509111725" l="RB58"/>
</s>


<s id="3251921554070049142-2509112000-7" eva="8000320">
    <ar ct="2509112026" l="RB54">
        <m id="r24796565" t="f" c="1000" ts="2509110453" ts-tts="25-09-11 04:54:13.950"/>
        <m id="r24796643" t="d" c="31" ts="2509110454" ts-tts="25-09-11 04:54:13.950"/>
    </ar>
</s>


<s id="4686009531619011137-2509111901-7" eva="8000320">
    <ar ct="2509111929" l="RB54">
        <m id="r24796587" t="f" c="1000" ts="2509110453" ts-tts="25-09-11 04:54:13.950"/>
        <m id="r24796645" t="d" c="31" ts="2509110454" ts-tts="25-09-11 04:54:13.950"/>
        <m id="r24796648" t="d" c="31" ts="2509110454" ts-tts="25-09-11 04:54:13.950"/>
    </ar>
    <dp ct="2509111932" l="RB54">
        <m id="r24796587" t="f" c="1000" ts="2509110453" ts-tts="25-09-11 04:54:13.950"/>
        <m id="r24796645" t="d" c="31" ts="2509110454" ts-tts="25-09-11 04:54:13.950"/>
        <m id="r24796648" t="d" c="31" ts="2509110454" ts-tts="25-09-11 04:54:13.950"/>
    </dp>
</s>


<s id="-2542295104078215143-2509111802-7" eva="8000320">
    <ar ct="2509111829" l="RB54">
        <m id="r24796576" t="f" c="1000" ts="2509110453" ts-tts="25-09-11 04:54:13.950"/>
        <m id="r24796656" t="d" c="31" ts="2509110454" ts-tts="25-09-11 04:54:13.950"/>
        <m id="r24796657" t="d" c="31" ts="2509110454" ts-tts="25-09-11 04:54:13.950"/>
    </ar>
    <dp ct="2509111832" l="RB54">
        <m id="r24796576" t="f" c="1000" ts="2509110453" ts-tts="25-09-11 04:54:13.950"/>
        <m id="r24796656" t="d" c="31" ts="2509110454" ts-tts="25-09-11 04:54:13.950"/>
        <m id="r24796657" t="d" c="31" ts="2509110454" ts-tts="25-09-11 04:54:13.950"/>
    </dp>
</s>


<s id="-6574981582705854968-2509111702-7" eva="8000320">
    <ar ct="2509111729" l="RB54">
        <m id="r24796569" t="f" c="1000" ts="2509110453" ts-tts="25-09-11 04:54:13.950"/>
        <m id="r24796649" t="d" c="31" ts="2509110454" ts-tts="25-09-11 04:54:13.950"/>
        <m id="r24796651" t="d" c="31" ts="2509110454" ts-tts="25-09-11 04:54:13.950"/>
    </ar>
    <dp ct="2509111732" l="RB54">
        <m id="r24796569" t="f" c="1000" ts="2509110453" ts-tts="25-09-11 04:54:13.950"/>
        <m id="r24796649" t="d" c="31" ts="2509110454" ts-tts="25-09-11 04:54:13.950"/>
        <m id="r24796651" t="d" c="31" ts="2509110454" ts-tts="25-09-11 04:54:13.950"/>
    </dp>
</s>


<s id="7445800921064315868-2509111602-7" eva="8000320">
    <ar ct="2509111629" l="RB54">
        <m id="r24796557" t="f" c="1000" ts="2509110453" ts-tts="25-09-11 04:54:13.950"/>
        <m id="r24796661" t="d" c="31" ts="2509110454" ts-tts="25-09-11 04:54:13.950"/>
        <m id="r24796664" t="d" c="31" ts="2509110454" ts-tts="25-09-11 04:54:13.950"/>
        <m id="r24796666" t="d" c="31" ts="2509110454" ts-tts="25-09-11 04:54:13.950"/>
    </ar>
    <dp ct="2509111632" l="RB54">
        <m id="r24796557" t="f" c="1000" ts="2509110453" ts-tts="25-09-11 04:54:13.950"/>
        <m id="r24796661" t="d" c="31" ts="2509110454" ts-tts="25-09-11 04:54:13.950"/>
        <m id="r24796664" t="d" c="31" ts="2509110454" ts-tts="25-09-11 04:54:13.950"/>
        <m id="r24796666" t="d" c="31" ts="2509110454" ts-tts="25-09-11 04:54:13.950"/>
    </dp>
</s>


<s id="-5841112343573447526-2509111502-7" eva="8000320">
    <ar ct="2509111529" l="RB54">
        <m id="r24796558" t="f" c="1000" ts="2509110453" ts-tts="25-09-11 04:54:13.950"/>
        <m id="r24796652" t="d" c="31" ts="2509110454" ts-tts="25-09-11 04:54:13.950"/>
    </ar>
    <dp ct="2509111532" l="RB54">
        <m id="r24796558" t="f" c="1000" ts="2509110453" ts-tts="25-09-11 04:54:13.950"/>
        <m id="r24796652" t="d" c="31" ts="2509110454" ts-tts="25-09-11 04:54:13.950"/>
    </dp>
</s>


<s id="1574480522637350862-2509112044-7" eva="8000320">
    <ar ct="2509112128" l="RB54">
        <m id="r24796599" t="f" c="1000" ts="2509110453" ts-tts="25-09-11 04:54:13.949"/>
        <m id="r24796668" t="d" c="31" ts="2509110454" ts-tts="25-09-11 04:54:13.949"/>
        <m id="r24796670" t="d" c="31" ts="2509110454" ts-tts="25-09-11 04:54:13.949"/>
    </ar>
    <dp ct="2509112135" l="RB54">
        <m id="r24796599" t="f" c="1000" ts="2509110453" ts-tts="25-09-11 04:54:13.949"/>
        <m id="r24796668" t="d" c="31" ts="2509110454" ts-tts="25-09-11 04:54:13.949"/>
        <m id="r24796670" t="d" c="31" ts="2509110454" ts-tts="25-09-11 04:54:13.949"/>
    </dp>
</s>


<s id="359750839819851966-2509111941-7" eva="8000320">
    <ar ct="2509112027" l="RB54">
        <m id="r24796597" t="f" c="1000" ts="2509110453" ts-tts="25-09-11 04:54:13.949"/>
        <m id="r24796658" t="d" c="31" ts="2509110454" ts-tts="25-09-11 04:54:13.949"/>
        <m id="r24796659" t="d" c="31" ts="2509110454" ts-tts="25-09-11 04:54:13.949"/>
    </ar>
    <dp ct="2509112035" l="RB54">
        <m id="r24796597" t="f" c="1000" ts="2509110453" ts-tts="25-09-11 04:54:13.949"/>
        <m id="r24796658" t="d" c="31" ts="2509110454" ts-tts="25-09-11 04:54:13.949"/>
        <m id="r24796659" t="d" c="31" ts="2509110454" ts-tts="25-09-11 04:54:13.949"/>
    </dp>
</s>


<s id="-3994644478874179945-2509111843-7" eva="8000320">
    <ar ct="2509111927" l="RB54">
        <m id="r24796575" t="f" c="1000" ts="2509110453" ts-tts="25-09-11 04:54:13.949"/>
        <m id="r24796667" t="d" c="31" ts="2509110454" ts-tts="25-09-11 04:54:13.949"/>
    </ar>
    <dp ct="2509111931" l="RB54">
        <m id="r24796575" t="f" c="1000" ts="2509110453" ts-tts="25-09-11 04:54:13.949"/>
        <m id="r24796667" t="d" c="31" ts="2509110454" ts-tts="25-09-11 04:54:13.949"/>
    </dp>
</s>


<s id="6065211906270254660-2509111822-7" eva="8000320">
    <ar ct="2509111906" l="RB54">
        <m id="r24796572" t="f" c="1000" ts="2509110453" ts-tts="25-09-11 04:54:13.949"/>
        <m id="r24796654" t="d" c="31" ts="2509110454" ts-tts="25-09-11 04:54:13.949"/>
    </ar>
    <dp ct="2509111908" l="RB54">
        <m id="r24796572" t="f" c="1000" ts="2509110453" ts-tts="25-09-11 04:54:13.949"/>
        <m id="r24796654" t="d" c="31" ts="2509110454" ts-tts="25-09-11 04:54:13.949"/>
    </dp>
</s>


<s id="-2454005409693185213-2509111741-7" eva="8000320">
    <ar ct="2509111824" l="RB54">
        <m id="r24796577" t="f" c="1000" ts="2509110453" ts-tts="25-09-11 04:54:13.949"/>
        <m id="r24796662" t="d" c="31" ts="2509110454" ts-tts="25-09-11 04:54:13.949"/>
        <m id="r24796663" t="d" c="31" ts="2509110454" ts-tts="25-09-11 04:54:13.949"/>
    </ar>
    <dp ct="2509111831" l="RB54">
        <m id="r24796577" t="f" c="1000" ts="2509110453" ts-tts="25-09-11 04:54:13.949"/>
        <m id="r24796662" t="d" c="31" ts="2509110454" ts-tts="25-09-11 04:54:13.949"/>
        <m id="r24796663" t="d" c="31" ts="2509110454" ts-tts="25-09-11 04:54:13.949"/>
    </dp>
</s>


<s id="3180057398976226452-2509111711-7" eva="8000320">
    <ar ct="2509111756" l="RB54">
        <m id="r24796561" t="f" c="1000" ts="2509110453" ts-tts="25-09-11 04:54:13.949"/>
        <m id="r24796634" t="d" c="31" ts="2509110454" ts-tts="25-09-11 04:54:13.949"/>
        <m id="r24796636" t="d" c="31" ts="2509110454" ts-tts="25-09-11 04:54:13.949"/>
        <m id="r24796639" t="d" c="31" ts="2509110454" ts-tts="25-09-11 04:54:13.949"/>
    </ar>
    <dp ct="2509111758" l="RB54">
        <m id="r24796561" t="f" c="1000" ts="2509110453" ts-tts="25-09-11 04:54:13.949"/>
        <m id="r24796634" t="d" c="31" ts="2509110454" ts-tts="25-09-11 04:54:13.949"/>
        <m id="r24796636" t="d" c="31" ts="2509110454" ts-tts="25-09-11 04:54:13.949"/>
        <m id="r24796639" t="d" c="31" ts="2509110454" ts-tts="25-09-11 04:54:13.949"/>
    </dp>
</s>


<s id="-3600681950845848130-2509111643-7" eva="8000320">
    <ar ct="2509111726" l="RB54">
        <m id="r24796567" t="f" c="1000" ts="2509110453" ts-tts="25-09-11 04:54:13.949"/>
        <m id="r24796628" t="d" c="31" ts="2509110454" ts-tts="25-09-11 04:54:13.949"/>
    </ar>
    <dp ct="2509111731" l="RB54">
        <m id="r24796567" t="f" c="1000" ts="2509110453" ts-tts="25-09-11 04:54:13.949"/>
        <m id="r24796628" t="d" c="31" ts="2509110454" ts-tts="25-09-11 04:54:13.949"/>
    </dp>
</s>


<s id="-8423739268267244618-2509111607-7" eva="8000320">
    <ar ct="2509111651" l="RB54">
        <m id="r24796564" t="f" c="1000" ts="2509110453" ts-tts="25-09-11 04:54:13.949"/>
        <m id="r24796635" t="d" c="31" ts="2509110454" ts-tts="25-09-11 04:54:13.949"/>
    </ar>
    <dp ct="2509111653" l="RB54">
        <m id="r24796564" t="f" c="1000" ts="2509110453" ts-tts="25-09-11 04:54:13.949"/>
        <m id="r24796635" t="d" c="31" ts="2509110454" ts-tts="25-09-11 04:54:13.949"/>
    </dp>
</s>


<s id="7266033375948408451-2509111541-7" eva="8000320">
    <ar ct="2509111624" l="RB54">
        <m id="r24796552" t="f" c="1000" ts="2509110453" ts-tts="25-09-11 04:54:13.949"/>
        <m id="r24796627" t="d" c="31" ts="2509110454" ts-tts="25-09-11 04:54:13.949"/>
    </ar>
    <dp ct="2509111631" l="RB54">
        <m id="r24796552" t="f" c="1000" ts="2509110453" ts-tts="25-09-11 04:54:13.949"/>
        <m id="r24796627" t="d" c="31" ts="2509110454" ts-tts="25-09-11 04:54:13.949"/>
    </dp>
</s>


<s id="2402416574276818535-2509111441-7" eva="8000320">
    <ar ct="2509111524" l="RB54">
        <m id="r24796560" t="f" c="1000" ts="2509110453" ts-tts="25-09-11 04:54:13.949"/>
        <m id="r24796638" t="d" c="31" ts="2509110454" ts-tts="25-09-11 04:54:13.949"/>
        <m id="r24796642" t="d" c="31" ts="2509110454" ts-tts="25-09-11 04:54:13.949"/>
    </ar>
    <dp ct="2509111531" l="RB54">
        <m id="r24796560" t="f" c="1000" ts="2509110453" ts-tts="25-09-11 04:54:13.949"/>
        <m id="r24796638" t="d" c="31" ts="2509110454" ts-tts="25-09-11 04:54:13.949"/>
        <m id="r24796642" t="d" c="31" ts="2509110454" ts-tts="25-09-11 04:54:13.949"/>
    </dp>
</s>


<s id="-7091436777592989374-2509111944-21" eva="8000320">
    <m id="r2488123" t="h" from="2509080000" to="2512132359" cat="Information" ts="2509080956" ts-tts="25-09-10 23:16:04.767" pr="1"/>
</s>


<s id="2609859235289006902-2509111808-10" eva="8000320">
    <ar cpth="Wien Westbahnhof|Wien Hütteldorf|St.Pölten Hbf|Amstetten NÖ|Linz Hbf|Wels Hbf|Attnang-Puchheim|Vöcklabruck|Salzburg Hbf" ct="2509112132">
        <m id="r24785348" t="f" c="1000" ts="2509102311" ts-tts="25-09-10 23:11:59.089"/>
        <m id="r24785422" t="f" c="0" ts="2509102312" ts-tts="25-09-10 23:12:45.718"/>
        <m id="r24785423" t="f" c="0" ts="2509102312" ts-tts="25-09-10 23:12:45.718"/>
    </ar>
    <dp cpth="München Hbf Gl.5-10" ct="2509112133">
        <m id="r24785348" t="f" c="1000" ts="2509102311" ts-tts="25-09-10 23:11:59.089"/>
        <m id="r24785422" t="f" c="0" ts="2509102312" ts-tts="25-09-10 23:12:45.718"/>
        <m id="r24785423" t="f" c="0" ts="2509102312" ts-tts="25-09-10 23:12:45.718"/>
    </dp>
</s>


<s id="-5117104799689341858-2509122345-1" eva="8000320">
    <dp ppth="Rohrdorf(Oberbay)" pp="4" pt="2509122345">
        <m id="r24533546" t="f" c="1000" ts="2509091006" ts-tts="25-09-09 10:06:21.875"/>
    </dp>
    <tl t="s" o="RISSDZ" c="DZ" n="27792"/>
</s>


<s id="2782488249911377063-2509121729-2" eva="8000320">
    <ar ppth="Rohrdorf(Oberbay)" pp="2" pt="2509121752">
        <m id="r24533180" t="f" c="1000" ts="2509091003" ts-tts="25-09-09 10:03:44.321"/>
    </ar>
    <tl t="s" o="RISSDZ" c="DZ" n="20183"/>
</s>


<s id="3178546308999030105-2509111813-7" eva="8000320">
    <m id="r2488098" t="h" from="2509080000" to="2512132359" cat="Information" ts="2509080945" ts-tts="25-09-10 23:16:04.696" pr="1"/>
</s>


<s id="5949417852042325682-2509102029-6" eva="8000320">
    <ar ct="2509110026"/>
    <dp ct="2509110033"/>
</s>


<s id="6746955278691408993-2509102029-6" eva="8000320">
    <ar ct="2509110031"/>
</s>


<s id="8803799214306376762-2509111608-10" eva="8000320">
    <ar>
        <m id="r24785330" t="f" c="1000" ts="2509102311" ts-tts="25-09-10 23:11:28.102"/>
        <m id="r24785440" t="f" c="0" ts="2509102312" ts-tts="25-09-10 23:12:45.718"/>
        <m id="r24785441" t="f" c="0" ts="2509102312" ts-tts="25-09-10 23:12:45.718"/>
    </ar>
    <dp>
        <m id="r24785330" t="f" c="1000" ts="2509102311" ts-tts="25-09-10 23:11:28.102"/>
        <m id="r24785440" t="f" c="0" ts="2509102312" ts-tts="25-09-10 23:12:45.718"/>
        <m id="r24785441" t="f" c="0" ts="2509102312" ts-tts="25-09-10 23:12:45.718"/>
    </dp>
</s>


<s id="4190296551359392611-2509111555-11" eva="8000320">
    <m id="r2488123" t="h" from="2509080000" to="2512132359" cat="Information" ts="2509080956" ts-tts="25-09-10 23:16:04.767" pr="1"/>
</s>


<s id="-293311094429060174-2509111512-7" eva="8000320">
    <ar>
        <m id="r24785562" t="f" c="1000" ts="2509102314" ts-tts="25-09-10 23:14:34.517"/>
        <m id="r24785564" t="f" c="0" ts="2509102314" ts-tts="25-09-10 23:14:34.517"/>
        <m id="r24785565" t="f" c="0" ts="2509102314" ts-tts="25-09-10 23:14:34.517"/>
    </ar>
    <dp>
        <m id="r24785562" t="f" c="1000" ts="2509102314" ts-tts="25-09-10 23:14:34.517"/>
        <m id="r24785564" t="f" c="0" ts="2509102314" ts-tts="25-09-10 23:14:34.517"/>
        <m id="r24785565" t="f" c="0" ts="2509102314" ts-tts="25-09-10 23:14:34.517"/>
    </dp>
</s>


<s id="-6787252959983318285-2509111548-3" eva="8000320">
    <ar>
        <m id="r24785537" t="f" c="1000" ts="2509102313" ts-tts="25-09-10 23:14:03.502"/>
        <m id="r24785538" t="f" c="0" ts="2509102313" ts-tts="25-09-10 23:14:03.502"/>
        <m id="r24785539" t="f" c="0" ts="2509102313" ts-tts="25-09-10 23:14:03.502"/>
    </ar>
    <dp>
        <m id="r24785537" t="f" c="1000" ts="2509102313" ts-tts="25-09-10 23:14:03.502"/>
        <m id="r24785538" t="f" c="0" ts="2509102313" ts-tts="25-09-10 23:14:03.502"/>
        <m id="r24785539" t="f" c="0" ts="2509102313" ts-tts="25-09-10 23:14:03.502"/>
    </dp>
</s>


<s id="-7197225462697969391-2509111537-18" eva="8000320">
    <ar l="44">
        <m id="r24775497" t="f" c="0" ts="2509102051" ts-tts="25-09-10 20:51:44.561"/>
    </ar>
</s>


<s id="3272146161175325165-2509102046-5" eva="8000320">
    <ar ct="2509102201"/>
    <dp ct="2509102203"/>
</s>


<s id="-8677182982400525824-2509102046-5" eva="8000320">
    <ar ct="2509102201"/>
    <dp ct="2509102203"/>
</s>


<s id="1545083288729087211-2509102008-3" eva="8000320">
    <ar cp="4" ct="2509102050"/>
    <dp cp="4" ct="2509102051"/>
</s>


<s id="-7204643245680624085-2509102008-3" eva="8000320">
    <ar cp="4" ct="2509102050"/>
    <dp cp="4" ct="2509102051"/>
</s>


<s id="-4306781354872417925-2509101835-3" eva="8000320">
    <ar cp="4" ct="2509101918">
        <m id="r24758784" t="f" c="0" ts="2509101838" ts-tts="25-09-10 18:38:39.321"/>
        <m id="r24758785" t="d" c="43" ts="2509101838" ts-tts="25-09-10 18:38:39.321"/>
    </ar>
    <dp cp="4" ct="2509101922">
        <m id="r24758784" t="f" c="0" ts="2509101838" ts-tts="25-09-10 18:38:39.321"/>
        <m id="r24758785" t="d" c="43" ts="2509101838" ts-tts="25-09-10 18:38:39.321"/>
    </dp>
</s>


<s id="1495737828554880847-2509101835-3" eva="8000320">
    <ar cp="4" ct="2509101917"/>
    <dp cp="4" ct="2509101922"/>
</s>

</timetable>