<?xml version="1.0" ?><timetable station="Kassel Hbf" eva="8000193">

<s id="3805121877911733550-2502050614-11" eva="8000193">
    <ar ct="2502050715" l="83"/>
</s>


<s id="-6204500910952412985-2502050705-1" eva="8000193">
    <dp ct="2502050706" l="RE98"/>
</s>


<s id="4016020366538631086-2502050616-17" eva="8000193">
    <ar ct="2502050749" l="5">
        <m id="r13196580" t="d" c="43" ts="2502050654" ts-tts="25-02-05 06:54:23.959"/>
        <m id="r13197112" t="d" c="21" ts="2502050705" ts-tts="25-02-05 07:05:50.856"/>
    </ar>
</s>


<s id="-4218232252739946939-2502051105-1" eva="8000193">
    <dp ct="2502051105" l="RE98"/>
</s>


<s id="5508766083845590549-2502050555-15" eva="8000193">
    <ar ct="2502050655" l="RE98"/>
</s>


<s id="-2663833713396329541-2502050646-1" eva="8000193">
    <dp ct="2502050647" l="83"/>
</s>


<s id="7991778931015442680-2502050718-13" eva="8000193">
    <ar ct="2502050933" l="30"/>
</s>


<s id="1303858069510063445-2502050446-25" eva="8000193">
    <ar ct="2502050648" l="2"/>
    <dp ct="2502050653" l="2"/>
</s>


<s id="3625218908049626677-2502050846-1" eva="8000193">
    <dp ct="2502050852" l="83"/>
</s>


<s id="-2193730001657083658-2502051046-1" eva="8000193">
    <dp ct="2502051046" l="83"/>
</s>


<s id="-995702779682422882-2502050543-13" eva="8000193">
    <ar ct="2502050648" l="5"/>
</s>


<s id="2874625510607608743-2502050520-12" eva="8000193">
    <ar ct="2502050734" l="30">
        <m id="r13188974" t="q" c="85" ts="2502042224" ts-tts="25-02-04 22:24:51.869"/>
    </ar>
</s>


<s id="-5755808967379569964-2502051038-1" eva="8000193">
    <dp ct="2502051038" l="5"/>
</s>


<s id="-5168036272007764973-2502050706-10" eva="8000193">
    <m id="r2359691" t="h" from="2502010000" to="2502071548" cat="Bauarbeiten" ts="2501312302" ts-tts="25-02-04 23:16:04.421" pr="2"/>
    <ar ct="2502050804" l="39"/>
</s>


<s id="-3899274250200716713-2502050632-1" eva="8000193">
    <dp ct="2502050632" l="5"/>
</s>


<s id="-9034043993448210450-2502050532-15" eva="8000193">
    <ar ct="2502050631" l="RE98"/>
</s>


<s id="2099414438856208129-2502051020-17" eva="8000193">
    <ar ct="2502051147" l="5"/>
</s>


<s id="-3175115456155363115-2502051020-22" eva="8000193">
    <ar ct="2502051254" l="RE98"/>
</s>


<s id="-2833169629784464095-2502050505-19" eva="8000193">
    <ar ct="2502050621" l="5">
        <m id="r13193765" t="d" c="48" ts="2502050448" ts-tts="25-02-05 04:49:06.683"/>
    </ar>
</s>


<s id="1633469575550317846-2502050616-1" eva="8000193">
    <dp cp="13" ct="2502050617" l="83"/>
</s>


<s id="6261183378340177723-2502052223-1" eva="8000193">
    <m id="r2357918" t="h" from="2502040000" to="2502062359" cat="Bauarbeiten" ts="2502032302" ts-tts="25-02-04 23:16:04.399" pr="2"/>
    <dp l="30">
        <m id="r13189800" t="q" c="85" ts="2502042306" ts-tts="25-02-04 23:06:13.986"/>
    </dp>
</s>


<s id="246728975879673208-2502052242-1" eva="8000193">
    <m id="r2359691" t="h" from="2502010000" to="2502071548" cat="Bauarbeiten" ts="2501312302" ts-tts="25-02-04 23:16:04.421" pr="2"/>
</s>


<s id="-6664792722770456436-2502052214-10" eva="8000193">
    <m id="r2359691" t="h" from="2502010000" to="2502071548" cat="Bauarbeiten" ts="2501312302" ts-tts="25-02-04 23:16:04.421" pr="2"/>
</s>


<s id="-6875031833617336022-2502051014-11" eva="8000193">
    <ar ct="2502051113" l="83"/>
</s>


<s id="3798957206463461718-2502050514-11" eva="8000193">
    <ar ct="2502050614" l="83"/>
</s>


<s id="4827112021444509815-2502050611-1" eva="8000193">
    <dp ct="2502050611" l="5"/>
</s>


<s id="-7458363371021473983-2502051011-1" eva="8000193">
    <dp ct="2502051011" l="5"/>
</s>


<s id="-850101764605434930-2502051010-6" eva="8000193">
    <ar ct="2502051117" l="5"/>
</s>


<s id="-3224085666073470264-2502050546-1" eva="8000193">
    <dp ct="2502050546" l="9"/>
</s>


<s id="-7745278389392234278-2502050946-1" eva="8000193">
    <dp ct="2502050946" l="83"/>
</s>


<s id="-1561643102135566385-2502050616-16" eva="8000193">
    <ar ct="2502050754" l="38"/>
</s>


<s id="-6244748001499512117-2502050613-10" eva="8000193">
    <ar ct="2502050714" l="39"/>
</s>


<s id="-6606603801247140265-2502050423-16" eva="8000193">
    <ar ct="2502050541" l="9"/>
</s>


<s id="1002775810059925934-2502050938-1" eva="8000193">
    <dp ct="2502050938" l="5"/>
</s>


<s id="-433402074358546073-2502050535-1" eva="8000193">
    <dp ct="2502050535" l="5"/>
</s>


<s id="859910925091865979-2502050518-1" eva="8000193">
    <dp ct="2502050521" l="83">
        <m id="r13194134" t="d" c="48" ts="2502050524" ts-tts="25-02-05 05:24:40.244"/>
    </dp>
</s>


<s id="-2525280895165784453-2502050414-11" eva="8000193">
    <ar ct="2502050516" l="83">
        <m id="r13194137" t="d" c="43" ts="2502050524" ts-tts="25-02-05 05:24:40.244"/>
    </ar>
</s>


<s id="5511206155939579440-2502050922-6" eva="8000193">
    <ar ct="2502051017" l="5"/>
</s>


<s id="6518838395635055693-2502050920-17" eva="8000193">
    <ar ct="2502051047" l="5"/>
</s>


<s id="260198625280724309-2502052142-1" eva="8000193">
    <m id="r2359691" t="h" from="2502010000" to="2502071548" cat="Bauarbeiten" ts="2501312302" ts-tts="25-02-04 23:16:04.421" pr="2"/>
</s>


<s id="4643363042718558097-2502052106-15" eva="8000193">
    <m id="r2359691" t="h" from="2502010000" to="2502071548" cat="Bauarbeiten" ts="2501312302" ts-tts="25-02-04 23:16:04.421" pr="2"/>
</s>


<s id="-5631025307629861397-2502050914-11" eva="8000193">
    <ar ct="2502051013" l="83"/>
</s>


<s id="3512962734845260457-2502050911-1" eva="8000193">
    <dp ct="2502050911" l="5"/>
</s>


<s id="9063475610523621624-2502050415-17" eva="8000193">
    <ar ct="2502050512" l="5"/>
</s>


<s id="-3496950169208817148-2502050505-1" eva="8000193">
    <dp ct="2502050506" l="5"/>
</s>


<s id="-7710914094412173264-2502050905-1" eva="8000193">
    <dp ct="2502050905" l="RE98"/>
</s>


<s id="9025044329296673090-2502050451-1" eva="8000193">
    <dp ct="2502050451" l="38"/>
</s>


<s id="1251800585546924282-2502050838-1" eva="8000193">
    <dp ct="2502050838" l="5"/>
</s>


<s id="8571383866859695429-2502050820-17" eva="8000193">
    <ar ct="2502050947" l="5"/>
</s>


<s id="5671758767956287500-2502050820-6" eva="8000193">
    <ar ct="2502050917" l="5"/>
</s>


<s id="-7061913212630267061-2502050820-22" eva="8000193">
    <ar ct="2502051055" l="RE98"/>
</s>


<s id="-4795658301093541517-2502050416-1" eva="8000193">
    <dp ct="2502050416" l="9"/>
</s>


<s id="-5338511536951306589-2502052042-1" eva="8000193">
    <m id="r2359691" t="h" from="2502010000" to="2502071548" cat="Bauarbeiten" ts="2501312302" ts-tts="25-02-04 23:16:04.421" pr="2"/>
</s>


<s id="-357304454883662583-2502052014-14" eva="8000193">
    <m id="r2359691" t="h" from="2502010000" to="2502071548" cat="Bauarbeiten" ts="2501312302" ts-tts="25-02-04 23:16:04.421" pr="2"/>
</s>


<s id="7909079333769130460-2502052023-1" eva="8000193">
    <m id="r2357918" t="h" from="2502040000" to="2502062359" cat="Bauarbeiten" ts="2502032302" ts-tts="25-02-04 23:16:04.399" pr="2"/>
    <m id="r2356587" t="h" from="2502052023" to="2502052241" cat="Bauarbeiten" ts="2502042302" ts-tts="25-02-04 23:02:36.810" pr="2"/>
</s>


<s id="-3773327377672299913-2502050814-11" eva="8000193">
    <ar ct="2502050913" l="83"/>
</s>


<s id="-4960162711959415680-2502050811-1" eva="8000193">
    <dp ct="2502050811" l="5"/>
</s>


<s id="7481393101923304569-2502050403-1" eva="8000193">
    <m id="r2357918" t="h" from="2502040000" to="2502062359" cat="Bauarbeiten" ts="2502032302" ts-tts="25-02-04 23:16:04.399" pr="2"/>
    <dp ct="2502050403" l="30"/>
</s>


<s id="-6871792213021682959-2502050355-1" eva="8000193">
    <dp ct="2502050355" l="5"/>
</s>


<s id="7634048245823543028-2502050748-11" eva="8000193">
    <ar ct="2502050843" l="83"/>
</s>


<s id="-422658052772671661-2502050746-1" eva="8000193">
    <dp ct="2502050746" l="83"/>
</s>


<s id="2968391540195162021-2502050738-1" eva="8000193">
    <dp ct="2502050738" l="5"/>
</s>


<s id="-5223891740501700221-2502050720-17" eva="8000193">
    <ar ct="2502050847" l="5"/>
</s>


<s id="1316609387146673789-2502050718-11" eva="8000193">
    <ar ct="2502050813" l="83"/>
</s>


<s id="-7908451041935798366-2502051918-12" eva="8000193">
    <ar l="30">
        <m id="r13189791" t="q" c="85" ts="2502042305" ts-tts="25-02-04 23:05:43.044"/>
    </ar>
</s>


<s id="-4454316160789495985-2502050711-1" eva="8000193">
    <dp ct="2502050711" l="5"/>
</s>


<s id="-1598789192310851557-2502050645-16" eva="8000193">
    <ar ct="2502050817" l="5"/>
</s>


<s id="5991996914789118563-2502050630-12" eva="8000193">
    <ar ct="2502050743" l="83"/>
</s>


<s id="3281170958201236190-2502050616-23" eva="8000193">
    <ar ct="2502050854" l="RE98"/>
</s>


<s id="3283072955374074575-2502051823-1" eva="8000193">
    <dp l="30">
        <m id="r13189854" t="q" c="85" ts="2502042308" ts-tts="25-02-04 23:08:33.733"/>
    </dp>
</s>


<s id="8176888926182179130-2502051839-1" eva="8000193">
    <m id="r2359691" t="h" from="2502010000" to="2502071548" cat="Bauarbeiten" ts="2501312302" ts-tts="25-02-04 23:16:04.421" pr="2"/>
</s>


<s id="-7759078687421136937-2502051814-12" eva="8000193">
    <m id="r2359691" t="h" from="2502010000" to="2502071548" cat="Bauarbeiten" ts="2501312302" ts-tts="25-02-04 23:16:04.421" pr="2"/>
</s>


<s id="-6427131056453296919-2502050548-16" eva="8000193">
    <ar ct="2502050717" l="5"/>
</s>


<s id="5557085164776573229-2502042309-23" eva="8000193">
    <ar ct="2502050043" l="5"/>
</s>


<s id="-5576614769303969245-2502042314-11" eva="8000193">
    <ar ct="2502050020" l="83">
        <m id="r13189610" t="d" c="21" ts="2502042257" ts-tts="25-02-04 22:57:26.958"/>
    </ar>
</s>


<s id="-7813105104775290827-2502051642-1" eva="8000193">
    <m id="r2359691" t="h" from="2502010000" to="2502071548" cat="Bauarbeiten" ts="2501312302" ts-tts="25-02-04 23:16:04.421" pr="2"/>
</s>


<s id="-9132152426797125010-2502051614-10" eva="8000193">
    <m id="r2359691" t="h" from="2502010000" to="2502071548" cat="Bauarbeiten" ts="2501312302" ts-tts="25-02-04 23:16:04.421" pr="2"/>
</s>


<s id="5588128401731872656-2502050011-1" eva="8000193">
    <dp ct="2502050012" l="5"/>
</s>


<s id="-8859366065824771350-2502042346-1" eva="8000193">
    <dp ct="2502042347" l="83"/>
</s>


<s id="-5660870276680990886-2502051506-15" eva="8000193">
    <m id="r2359691" t="h" from="2502010000" to="2502071548" cat="Bauarbeiten" ts="2501312302" ts-tts="25-02-04 23:16:04.421" pr="2"/>
</s>


<s id="-2761429407996405858-2502051442-1" eva="8000193">
    <m id="r2359691" t="h" from="2502010000" to="2502071548" cat="Bauarbeiten" ts="2501312302" ts-tts="25-02-04 23:16:04.421" pr="2"/>
</s>


<s id="718099137295354746-2502051414-14" eva="8000193">
    <m id="r2359691" t="h" from="2502010000" to="2502071548" cat="Bauarbeiten" ts="2501312302" ts-tts="25-02-04 23:16:04.421" pr="2"/>
</s>


<s id="-4901394115456491957-2502051239-1" eva="8000193">
    <m id="r2359691" t="h" from="2502010000" to="2502071548" cat="Bauarbeiten" ts="2501312302" ts-tts="25-02-04 23:16:04.421" pr="2"/>
</s>


<s id="-6967457789739878559-2502051214-12" eva="8000193">
    <m id="r2359691" t="h" from="2502010000" to="2502071548" cat="Bauarbeiten" ts="2501312302" ts-tts="25-02-04 23:16:04.421" pr="2"/>
</s>


<s id="7671755399322673223-2502051042-1" eva="8000193">
    <m id="r2359691" t="h" from="2502010000" to="2502071548" cat="Bauarbeiten" ts="2501312302" ts-tts="25-02-04 23:16:04.421" pr="2"/>
</s>


<s id="7260245737729833862-2502051014-10" eva="8000193">
    <m id="r2359691" t="h" from="2502010000" to="2502071548" cat="Bauarbeiten" ts="2501312302" ts-tts="25-02-04 23:16:04.421" pr="2"/>
</s>


<s id="-2786880414059545434-2502050842-1" eva="8000193">
    <m id="r2359691" t="h" from="2502010000" to="2502071548" cat="Bauarbeiten" ts="2501312302" ts-tts="25-02-04 23:16:04.421" pr="2"/>
</s>


<s id="-981870580973872963-2502051518-12" eva="8000193">
    <ar l="30">
        <m id="r13187140" t="f" c="0" ts="2502042109" ts-tts="25-02-04 21:09:51.351"/>
        <m id="r13189839" t="q" c="85" ts="2502042308" ts-tts="25-02-04 23:08:18.279"/>
    </ar>
</s>


<s id="8115543450324552150-2502042311-1" eva="8000193">
    <dp ct="2502042311" l="5"/>
</s>


<s id="7719758655801921606-2502051423-1" eva="8000193">
    <dp l="30">
        <m id="r13188997" t="q" c="85" ts="2502042225" ts-tts="25-02-04 22:25:38.424"/>
    </dp>
</s>


<s id="4298567271766791888-2502051120-12" eva="8000193">
    <ar l="30">
        <m id="r13188993" t="q" c="85" ts="2502042225" ts-tts="25-02-04 22:25:22.914"/>
    </ar>
</s>


<s id="357216455508944088-2502050823-1" eva="8000193">
    <dp l="30">
        <m id="r13188984" t="q" c="85" ts="2502042225" ts-tts="25-02-04 22:25:07.399"/>
    </dp>
</s>


<s id="3548469924766987265-2502051223-1" eva="8000193">
    <dp l="30">
        <m id="r13187119" t="f" c="0" ts="2502042108" ts-tts="25-02-04 21:08:48.454"/>
    </dp>
</s>


<s id="2655449694879832500-2502050920-12" eva="8000193">
    <ar l="30">
        <m id="r13187094" t="f" c="0" ts="2502042107" ts-tts="25-02-04 21:07:45.827"/>
        <m id="r13187095" t="f" c="0" ts="2502042107" ts-tts="25-02-04 21:08:01.467"/>
    </ar>
</s>


<s id="8542119838749842090-2502042220-26" eva="8000193">
    <m id="r2362855" t="h" from="2502040000" to="2502042359" cat="Bauarbeiten" ts="2502032302" ts-tts="25-02-03 23:03:00.576" pr="2"/>
    <ar cpth="Frankfurt(Main)Hbf|Friedberg(Hess)|Gießen" cs="c" clt="2502041753" l="RE98">
        <m id="r13179570" t="d" c="31" ts="2502041753" ts-tts="25-02-04 17:53:41.504"/>
    </ar>
</s>

</timetable>